<mc_data p_obs='77.15'>
 <sample theta_obs='1.44211'
     phi_obs='2.97803'
     theta_dev='0.0719786' />
 <sample theta_obs='1.30505'
     phi_obs='3.05334'
     theta_dev='0.14318' />
 <sample theta_obs='1.76947'
     phi_obs='3.59201'
     theta_dev='0.225031' />
 <sample theta_obs='1.64212'
     phi_obs='3.9566'
     theta_dev='0.127418' />
 <sample theta_obs='1.93866'
     phi_obs='2.16483'
     theta_dev='0.361681' />
 <sample theta_obs='0.350285'
     phi_obs='0.855465'
     theta_dev='0.843031' />
 <sample theta_obs='2.29589'
     phi_obs='5.81161'
     theta_dev='1.07799' />
 <sample theta_obs='0.949913'
     phi_obs='4.31813'
     theta_dev='0.35531' />
 <sample theta_obs='2.8135'
     phi_obs='3.22993'
     theta_dev='1.04286' />
 <sample theta_obs='0.670995'
     phi_obs='3.92037'
     theta_dev='0.426568' />
 <sample theta_obs='0.857867'
     phi_obs='5.689'
     theta_dev='0.883844' />
 <sample theta_obs='2.45199'
     phi_obs='1.67687'
     theta_dev='0.870596' />
 <sample theta_obs='2.63327'
     phi_obs='2.06536'
     theta_dev='0.971716' />
 <sample theta_obs='2.53321'
     phi_obs='1.30825'
     theta_dev='1.07239' />
 <sample theta_obs='1.2619'
     phi_obs='0.302291'
     theta_dev='1.30727' />
 <sample theta_obs='0.258318'
     phi_obs='1.00195'
     theta_dev='0.861741' />
 <sample theta_obs='0.680486'
     phi_obs='1.40042'
     theta_dev='0.691045' />
 <sample theta_obs='1.01588'
     phi_obs='3.2592'
     theta_dev='0.311007' />
 <sample theta_obs='0.437653'
     phi_obs='0.947504'
     theta_dev='0.856682' />
 <sample theta_obs='2.80984'
     phi_obs='2.43036'
     theta_dev='1.07696' />
 <sample theta_obs='0.956581'
     phi_obs='5.09153'
     theta_dev='0.555444' />
 <sample theta_obs='1.02022'
     phi_obs='5.23179'
     theta_dev='0.556113' />
 <sample theta_obs='1.42927'
     phi_obs='4.28414'
     theta_dev='0.0439175' />
 <sample theta_obs='2.23135'
     phi_obs='5.98779'
     theta_dev='1.16175' />
 <sample theta_obs='0.506628'
     phi_obs='3.34336'
     theta_dev='0.530488' />
 <sample theta_obs='2.26612'
     phi_obs='5.14027'
     theta_dev='0.756602' />
 <sample theta_obs='0.902885'
     phi_obs='4.4051'
     theta_dev='0.396777' />
 <sample theta_obs='1.48787'
     phi_obs='2.22576'
     theta_dev='0.0690682' />
 <sample theta_obs='1.45744'
     phi_obs='5.19329'
     theta_dev='0.147651' />
 <sample theta_obs='2.50227'
     phi_obs='1.09042'
     theta_dev='1.10731' />
 <sample theta_obs='2.07148'
     phi_obs='0.726245'
     theta_dev='0.653417' />
 <sample theta_obs='0.954465'
     phi_obs='4.13676'
     theta_dev='0.332657' />
 <sample theta_obs='0.469171'
     phi_obs='4.00036'
     theta_dev='0.140436' />
 <sample theta_obs='2.45107'
     phi_obs='1.53738'
     theta_dev='0.898244' />
 <sample theta_obs='2.74074'
     phi_obs='4.05442'
     theta_dev='1.01395' />
 <sample theta_obs='0.639093'
     phi_obs='5.75744'
     theta_dev='0.900209' />
 <sample theta_obs='0.336307'
     phi_obs='4.01718'
     theta_dev='0.246123' />
 <sample theta_obs='2.19499'
     phi_obs='0.235727'
     theta_dev='1.62145' />
 <sample theta_obs='1.07846'
     phi_obs='4.14435'
     theta_dev='0.266657' />
 <sample theta_obs='1.78734'
     phi_obs='2.99429'
     theta_dev='0.235325' />
 <sample theta_obs='2.17724'
     phi_obs='2.71531'
     theta_dev='0.541982' />
 <sample theta_obs='1.15898'
     phi_obs='2.09811'
     theta_dev='0.325393' />
 <sample theta_obs='0.584594'
     phi_obs='2.2938'
     theta_dev='0.821975' />
 <sample theta_obs='1.674'
     phi_obs='5.14734'
     theta_dev='0.124975' />
 <sample theta_obs='0.905117'
     phi_obs='2.83748'
     theta_dev='0.436844' />
 <sample theta_obs='3.13068'
     phi_obs='3.49819'
     theta_dev='1.2949' />
 <sample theta_obs='1.3846'
     phi_obs='3.74942'
     theta_dev='0.0668277' />
 <sample theta_obs='0.401374'
     phi_obs='5.74131'
     theta_dev='0.742079' />
 <sample theta_obs='2.37745'
     phi_obs='1.6321'
     theta_dev='0.808285' />
 <sample theta_obs='0.273555'
     phi_obs='3.62756'
     theta_dev='0.520558' />
 <sample theta_obs='2.51825'
     phi_obs='5.63303'
     theta_dev='1.16503' />
 <sample theta_obs='0.806474'
     phi_obs='5.06895'
     theta_dev='0.648055' />
 <sample theta_obs='3.03152'
     phi_obs='1.81374'
     theta_dev='1.29032' />
 <sample theta_obs='1.39414'
     phi_obs='6.10646'
     theta_dev='1.04312' />
 <sample theta_obs='0.734746'
     phi_obs='6.20813'
     theta_dev='1.1041' />
 <sample theta_obs='2.53755'
     phi_obs='0.659495'
     theta_dev='1.31248' />
 <sample theta_obs='1.11564'
     phi_obs='5.30096'
     theta_dev='0.50396' />
 <sample theta_obs='0.53261'
     phi_obs='3.29133'
     theta_dev='0.560856' />
 <sample theta_obs='0.679752'
     phi_obs='4.32932'
     theta_dev='0.425074' />
 <sample theta_obs='2.29115'
     phi_obs='1.72944'
     theta_dev='0.712491' />
 <sample theta_obs='1.69996'
     phi_obs='6.10557'
     theta_dev='1.48627' />
 <sample theta_obs='2.60389'
     phi_obs='4.04458'
     theta_dev='0.904704' />
 <sample theta_obs='1.28324'
     phi_obs='0.130351'
     theta_dev='2.56941' />
 <sample theta_obs='3.06449'
     phi_obs='4.547'
     theta_dev='1.27185' />
 <sample theta_obs='3.0267'
     phi_obs='0.590184'
     theta_dev='1.42334' />
 <sample theta_obs='0.467742'
     phi_obs='3.73744'
     theta_dev='0.29649' />
 <sample theta_obs='2.95417'
     phi_obs='4.64014'
     theta_dev='1.22157' />
 <sample theta_obs='0.757131'
     phi_obs='5.38108'
     theta_dev='0.746232' />
 <sample theta_obs='1.35377'
     phi_obs='6.27264'
     theta_dev='2.41693' />
 <sample theta_obs='0.234009'
     phi_obs='5.84497'
     theta_dev='0.384781' />
 <sample theta_obs='0.624556'
     phi_obs='3.79632'
     theta_dev='0.4153' />
 <sample theta_obs='2.30112'
     phi_obs='1.25386'
     theta_dev='0.814382' />
 <sample theta_obs='2.07193'
     phi_obs='3.11792'
     theta_dev='0.454531' />
 <sample theta_obs='2.31875'
     phi_obs='5.85256'
     theta_dev='1.12394' />
 <sample theta_obs='0.872338'
     phi_obs='5.74036'
     theta_dev='0.954737' />
 <sample theta_obs='1.48993'
     phi_obs='5.66325'
     theta_dev='0.192668' />
 <sample theta_obs='1.69266'
     phi_obs='2.31536'
     theta_dev='0.157488' />
 <sample theta_obs='2.87053'
     phi_obs='0.0607012'
     theta_dev='1.49945' />
 <sample theta_obs='1.74796'
     phi_obs='2.89451'
     theta_dev='0.205313' />
 <sample theta_obs='2.86695'
     phi_obs='3.09589'
     theta_dev='1.08691' />
 <sample theta_obs='1.24632'
     phi_obs='3.1762'
     theta_dev='0.173149' />
 <sample theta_obs='2.27247'
     phi_obs='0.126526'
     theta_dev='1.59626' />
 <sample theta_obs='2.66469'
     phi_obs='4.34445'
     theta_dev='0.980585' />
 <sample theta_obs='0.949998'
     phi_obs='5.10122'
     theta_dev='0.563296' />
 <sample theta_obs='0.251411'
     phi_obs='2.47132'
     theta_dev='0.952593' />
 <sample theta_obs='1.94475'
     phi_obs='0.641306'
     theta_dev='0.649' />
 <sample theta_obs='1.19724'
     phi_obs='0.137391'
     theta_dev='2.51157' />
 <sample theta_obs='1.81477'
     phi_obs='5.56647'
     theta_dev='0.361362' />
 <sample theta_obs='0.016628'
     phi_obs='0.708075'
     theta_dev='0.655482' />
 <sample theta_obs='0.0972297'
     phi_obs='4.40399'
     theta_dev='0.508324' />
 <sample theta_obs='1.90834'
     phi_obs='6.15613'
     theta_dev='1.27087' />
 <sample theta_obs='1.13369'
     phi_obs='1.15582'
     theta_dev='0.320014' />
 <sample theta_obs='1.39848'
     phi_obs='0.750338'
     theta_dev='0.498134' />
 <sample theta_obs='2.07417'
     phi_obs='1.70085'
     theta_dev='0.51755' />
 <sample theta_obs='0.734024'
     phi_obs='4.5282'
     theta_dev='0.483959' />
 <sample theta_obs='2.41624'
     phi_obs='5.71256'
     theta_dev='1.12088' />
 <sample theta_obs='1.43018'
     phi_obs='5.9481'
     theta_dev='0.845208' />
 <sample theta_obs='2.64518'
     phi_obs='1.83916'
     theta_dev='1.01872' />
 <sample theta_obs='0.400209'
     phi_obs='4.51015'
     theta_dev='0.231984' />
 <sample theta_obs='0.202112'
     phi_obs='5.7732'
     theta_dev='0.364293' />
 <sample theta_obs='0.144032'
     phi_obs='4.70825'
     theta_dev='0.407013' />
 <sample theta_obs='1.01122'
     phi_obs='1.03659'
     theta_dev='0.428107' />
 <sample theta_obs='1.10521'
     phi_obs='0.714499'
     theta_dev='0.365726' />
 <sample theta_obs='2.84931'
     phi_obs='2.91549'
     theta_dev='1.07793' />
 <sample theta_obs='0.75405'
     phi_obs='1.44693'
     theta_dev='0.636893' />
 <sample theta_obs='2.34905'
     phi_obs='3.09899'
     theta_dev='0.673818' />
 <sample theta_obs='1.75784'
     phi_obs='4.98122'
     theta_dev='0.210776' />
 <sample theta_obs='1.02612'
     phi_obs='2.82609'
     theta_dev='0.352114' />
 <sample theta_obs='2.29624'
     phi_obs='1.04284'
     theta_dev='0.87346' />
 <sample theta_obs='2.7029'
     phi_obs='4.80795'
     theta_dev='1.07607' />
 <sample theta_obs='1.29203'
     phi_obs='5.62026'
     theta_dev='0.41946' />
 <sample theta_obs='0.251118'
     phi_obs='3.70202'
     theta_dev='0.513714' />
 <sample theta_obs='1.12901'
     phi_obs='2.2777'
     theta_dev='0.338373' />
 <sample theta_obs='2.29717'
     phi_obs='4.48151'
     theta_dev='0.685109' />
 <sample theta_obs='1.19163'
     phi_obs='1.21779'
     theta_dev='0.272089' />
 <sample theta_obs='1.71977'
     phi_obs='6.20133'
     theta_dev='1.71993' />
 <sample theta_obs='1.53081'
     phi_obs='3.14086'
     theta_dev='0.0682989' />
 <sample theta_obs='2.80968'
     phi_obs='1.3538'
     theta_dev='1.296' />
 <sample theta_obs='2.92762'
     phi_obs='4.40563'
     theta_dev='1.18217' />
 <sample theta_obs='1.11645'
     phi_obs='5.61015'
     theta_dev='0.608984' />
 <sample theta_obs='2.48689'
     phi_obs='0.80179'
     theta_dev='1.16392' />
 <sample theta_obs='2.87465'
     phi_obs='5.09986'
     theta_dev='1.24215' />
 <sample theta_obs='2.33865'
     phi_obs='4.32549'
     theta_dev='0.707324' />
 <sample theta_obs='2.70808'
     phi_obs='2.21123'
     theta_dev='1.01665' />
 <sample theta_obs='3.08996'
     phi_obs='5.89763'
     theta_dev='1.33638' />
 <sample theta_obs='2.98325'
     phi_obs='6.09042'
     theta_dev='1.41724' />
 <sample theta_obs='2.24302'
     phi_obs='1.17451'
     theta_dev='0.773633' />
 <sample theta_obs='0.766285'
     phi_obs='1.8511'
     theta_dev='0.687885' />
 <sample theta_obs='0.656038'
     phi_obs='5.88112'
     theta_dev='0.954337' />
 <sample theta_obs='2.95102'
     phi_obs='4.87881'
     theta_dev='1.24677' />
 <sample theta_obs='0.356049'
     phi_obs='2.51702'
     theta_dev='0.948949' />
 <sample theta_obs='0.378762'
     phi_obs='5.46344'
     theta_dev='0.706357' />
 <sample theta_obs='0.868064'
     phi_obs='0.826369'
     theta_dev='0.55339' />
 <sample theta_obs='2.04859'
     phi_obs='3.3954'
     theta_dev='0.43783' />
 <sample theta_obs='1.0173'
     phi_obs='3.81879'
     theta_dev='0.286924' />
 <sample theta_obs='2.20636'
     phi_obs='5.42891'
     theta_dev='0.784111' />
 <sample theta_obs='1.30166'
     phi_obs='4.74232'
     theta_dev='0.193297' />
 <sample theta_obs='2.26878'
     phi_obs='0.08835'
     theta_dev='1.52647' />
 <sample theta_obs='2.97137'
     phi_obs='6.0594'
     theta_dev='1.4201' />
 <sample theta_obs='2.95872'
     phi_obs='5.36912'
     theta_dev='1.31595' />
 <sample theta_obs='3.11141'
     phi_obs='3.40814'
     theta_dev='1.27903' />
 <sample theta_obs='2.50274'
     phi_obs='0.120965'
     theta_dev='1.56968' />
 <sample theta_obs='2.59032'
     phi_obs='2.82715'
     theta_dev='0.873174' />
 <sample theta_obs='1.2177'
     phi_obs='5.19284'
     theta_dev='0.381692' />
 <sample theta_obs='1.91128'
     phi_obs='1.89946'
     theta_dev='0.351659' />
 <sample theta_obs='1.87879'
     phi_obs='2.83429'
     theta_dev='0.304072' />
 <sample theta_obs='0.714197'
     phi_obs='2.10263'
     theta_dev='0.723626' />
 <sample theta_obs='0.743646'
     phi_obs='4.03537'
     theta_dev='0.442904' />
 <sample theta_obs='0.968417'
     phi_obs='2.77037'
     theta_dev='0.401348' />
 <sample theta_obs='1.07009'
     phi_obs='0.860999'
     theta_dev='0.384707' />
 <sample theta_obs='1.25818'
     phi_obs='1.16155'
     theta_dev='0.230593' />
 <sample theta_obs='0.128941'
     phi_obs='4.79628'
     theta_dev='0.417968' />
 <sample theta_obs='1.25139'
     phi_obs='3.36513'
     theta_dev='0.160081' />
 <sample theta_obs='0.284933'
     phi_obs='3.45769'
     theta_dev='0.592983' />
 <sample theta_obs='1.71165'
     phi_obs='1.31439'
     theta_dev='0.248603' />
 <sample theta_obs='2.1969'
     phi_obs='3.78961'
     theta_dev='0.562234' />
 <sample theta_obs='0.696588'
     phi_obs='0.190522'
     theta_dev='0.771161' />
 <sample theta_obs='1.38542'
     phi_obs='0.386421'
     theta_dev='2.79541' />
 <sample theta_obs='2.35013'
     phi_obs='0.729852'
     theta_dev='0.999066' />
 <sample theta_obs='2.11784'
     phi_obs='5.23806'
     theta_dev='0.626298' />
 <sample theta_obs='2.26313'
     phi_obs='4.245'
     theta_dev='0.637274' />
 <sample theta_obs='1.5799'
     phi_obs='0.698078'
     theta_dev='0.541045' />
 <sample theta_obs='2.1266'
     phi_obs='0.535205'
     theta_dev='1.1252' />
 <sample theta_obs='2.82517'
     phi_obs='3.94531'
     theta_dev='1.07174' />
 <sample theta_obs='0.972599'
     phi_obs='3.38135'
     theta_dev='0.326538' />
 <sample theta_obs='2.01345'
     phi_obs='2.905'
     theta_dev='0.409012' />
 <sample theta_obs='0.324153'
     phi_obs='0.588713'
     theta_dev='0.736797' />
 <sample theta_obs='1.19187'
     phi_obs='1.92293'
     theta_dev='0.300771' />
 <sample theta_obs='3.11485'
     phi_obs='4.37321'
     theta_dev='1.29067' />
 <sample theta_obs='2.73231'
     phi_obs='5.14464'
     theta_dev='1.16612' />
 <sample theta_obs='1.84905'
     phi_obs='2.67182'
     theta_dev='0.281404' />
 <sample theta_obs='0.959624'
     phi_obs='1.26105'
     theta_dev='0.4677' />
 <sample theta_obs='1.50055'
     phi_obs='1.01899'
     theta_dev='0.252402' />
 <sample theta_obs='2.15983'
     phi_obs='5.34171'
     theta_dev='0.702208' />
 <sample theta_obs='0.628889'
     phi_obs='5.45878'
     theta_dev='0.809619' />
 <sample theta_obs='0.00149962'
     phi_obs='4.35001'
     theta_dev='0.645328' />
 <sample theta_obs='0.215103'
     phi_obs='1.48339'
     theta_dev='0.942256' />
 <sample theta_obs='0.980579'
     phi_obs='5.03946'
     theta_dev='0.520751' />
 <sample theta_obs='0.883779'
     phi_obs='2.76178'
     theta_dev='0.465689' />
 <sample theta_obs='2.18359'
     phi_obs='5.33161'
     theta_dev='0.724517' />
 <sample theta_obs='2.38031'
     phi_obs='5.78725'
     theta_dev='1.13261' />
 <sample theta_obs='2.3214'
     phi_obs='1.78686'
     theta_dev='0.732108' />
 <sample theta_obs='3.0586'
     phi_obs='1.56376'
     theta_dev='1.31567' />
 <sample theta_obs='0.73308'
     phi_obs='4.00688'
     theta_dev='0.434828' />
 <sample theta_obs='3.10083'
     phi_obs='4.7204'
     theta_dev='1.29317' />
 <sample theta_obs='0.0676573'
     phi_obs='2.33266'
     theta_dev='0.7872' />
 <sample theta_obs='1.81268'
     phi_obs='1.14885'
     theta_dev='0.379501' />
 <sample theta_obs='2.62063'
     phi_obs='0.700199'
     theta_dev='1.39055' />
 <sample theta_obs='1.03491'
     phi_obs='0.0297043'
     theta_dev='2.16044' />
 <sample theta_obs='0.0270682'
     phi_obs='5.02745'
     theta_dev='0.588635' />
 <sample theta_obs='2.26729'
     phi_obs='5.43127'
     theta_dev='0.84882' />
 <sample theta_obs='0.919479'
     phi_obs='4.99569'
     theta_dev='0.548094' />
 <sample theta_obs='1.16403'
     phi_obs='1.64565'
     theta_dev='0.317184' />
 <sample theta_obs='2.5439'
     phi_obs='2.29972'
     theta_dev='0.868469' />
 <sample theta_obs='0.685305'
     phi_obs='3.71614'
     theta_dev='0.430643' />
 <sample theta_obs='1.42895'
     phi_obs='4.20085'
     theta_dev='0.0402785' />
 <sample theta_obs='2.35881'
     phi_obs='4.91115'
     theta_dev='0.798496' />
 <sample theta_obs='1.11869'
     phi_obs='1.40004'
     theta_dev='0.339884' />
 <sample theta_obs='1.79945'
     phi_obs='3.10137'
     theta_dev='0.245087' />
 <sample theta_obs='0.111226'
     phi_obs='1.24572'
     theta_dev='0.82305' />
 <sample theta_obs='3.09523'
     phi_obs='5.63172'
     theta_dev='1.32489' />
 <sample theta_obs='3.02294'
     phi_obs='4.53028'
     theta_dev='1.24998' />
 <sample theta_obs='1.42262'
     phi_obs='3.08773'
     theta_dev='0.0743668' />
 <sample theta_obs='2.66521'
     phi_obs='1.92395'
     theta_dev='1.02128' />
 <sample theta_obs='2.83627'
     phi_obs='1.67822'
     theta_dev='1.21651' />
 <sample theta_obs='3.1042'
     phi_obs='5.37317'
     theta_dev='1.31379' />
 <sample theta_obs='0.379062'
     phi_obs='3.29997'
     theta_dev='0.604159' />
 <sample theta_obs='0.0413766'
     phi_obs='3.55014'
     theta_dev='0.654318' />
 <sample theta_obs='0.416584'
     phi_obs='5.26166'
     theta_dev='0.726892' />
 <sample theta_obs='0.533631'
     phi_obs='5.86134'
     theta_dev='0.899495' />
 <sample theta_obs='1.07696'
     phi_obs='1.94958'
     theta_dev='0.403824' />
 <sample theta_obs='0.662441'
     phi_obs='3.96659'
     theta_dev='0.424332' />
 <sample theta_obs='0.239598'
     phi_obs='6.1004'
     theta_dev='0.385986' />
 <sample theta_obs='2.49434'
     phi_obs='1.5184'
     theta_dev='0.945992' />
 <sample theta_obs='2.06441'
     phi_obs='2.82208'
     theta_dev='0.449837' />
 <sample theta_obs='1.96222'
     phi_obs='2.01889'
     theta_dev='0.389086' />
 <sample theta_obs='1.69631'
     phi_obs='1.66648'
     theta_dev='0.174422' />
 <sample theta_obs='0.190357'
     phi_obs='4.67609'
     theta_dev='0.360178' />
 <sample theta_obs='0.480703'
     phi_obs='2.21987'
     theta_dev='0.926744' />
 <sample theta_obs='1.25506'
     phi_obs='2.22779'
     theta_dev='0.237224' />
 <sample theta_obs='1.27779'
     phi_obs='3.90402'
     theta_dev='0.135043' />
 <sample theta_obs='0.677728'
     phi_obs='2.21664'
     theta_dev='0.744094' />
 <sample theta_obs='1.66371'
     phi_obs='3.72158'
     theta_dev='0.146261' />
 <sample theta_obs='0.0968507'
     phi_obs='4.62431'
     theta_dev='0.482225' />
 <sample theta_obs='1.71853'
     phi_obs='0.419984'
     theta_dev='1.88275' />
 <sample theta_obs='1.92748'
     phi_obs='5.70465'
     theta_dev='0.616911' />
 <sample theta_obs='0.953436'
     phi_obs='3.93466'
     theta_dev='0.321858' />
 <sample theta_obs='0.943077'
     phi_obs='0.49185'
     theta_dev='0.386057' />
 <sample theta_obs='0.800204'
     phi_obs='0.465199'
     theta_dev='0.463928' />
 <sample theta_obs='2.54692'
     phi_obs='3.71312'
     theta_dev='0.840595' />
 <sample theta_obs='0.967649'
     phi_obs='5.0442'
     theta_dev='0.531517' />
 <sample theta_obs='0.456476'
     phi_obs='0.746549'
     theta_dev='0.8407' />
 <sample theta_obs='3.05903'
     phi_obs='4.40976'
     theta_dev='1.26243' />
 <sample theta_obs='1.07233'
     phi_obs='2.00714'
     theta_dev='0.40609' />
 <sample theta_obs='2.47548'
     phi_obs='5.58455'
     theta_dev='1.10946' />
 <sample theta_obs='1.99383'
     phi_obs='2.70696'
     theta_dev='0.394876' />
 <sample theta_obs='2.53454'
     phi_obs='4.29172'
     theta_dev='0.869117' />
 <sample theta_obs='2.41151'
     phi_obs='4.67262'
     theta_dev='0.808435' />
 <sample theta_obs='1.83051'
     phi_obs='3.64678'
     theta_dev='0.271457' />
 <sample theta_obs='0.288272'
     phi_obs='2.22667'
     theta_dev='0.968633' />
 <sample theta_obs='0.0124393'
     phi_obs='5.49313'
     theta_dev='0.620745' />
 <sample theta_obs='1.27743'
     phi_obs='2.10191'
     theta_dev='0.223302' />
 <sample theta_obs='2.44517'
     phi_obs='2.16055'
     theta_dev='0.797489' />
 <sample theta_obs='0.109476'
     phi_obs='5.5224'
     theta_dev='0.427528' />
 <sample theta_obs='0.169697'
     phi_obs='5.83691'
     theta_dev='0.376354' />
 <sample theta_obs='0.860228'
     phi_obs='4.51409'
     theta_dev='0.459563' />
 <sample theta_obs='0.192267'
     phi_obs='2.73125'
     theta_dev='0.886114' />
 <sample theta_obs='0.929985'
     phi_obs='6.02702'
     theta_dev='1.54392' />
 <sample theta_obs='2.73235'
     phi_obs='5.69634'
     theta_dev='1.32358' />
 <sample theta_obs='0.419771'
     phi_obs='1.00487'
     theta_dev='0.8728' />
 <sample theta_obs='1.92317'
     phi_obs='5.4545'
     theta_dev='0.464563' />
 <sample theta_obs='0.419354'
     phi_obs='5.19144'
     theta_dev='0.723545' />
 <sample theta_obs='1.60663'
     phi_obs='4.23056'
     theta_dev='0.0939951' />
 <sample theta_obs='0.022748'
     phi_obs='2.27494'
     theta_dev='0.697364' />
 <sample theta_obs='1.07247'
     phi_obs='0.113755'
     theta_dev='2.21969' />
 <sample theta_obs='3.09018'
     phi_obs='0.198581'
     theta_dev='1.34806' />
 <sample theta_obs='1.06903'
     phi_obs='0.50216'
     theta_dev='0.357214' />
 <sample theta_obs='0.242681'
     phi_obs='3.68541'
     theta_dev='0.530641' />
 <sample theta_obs='0.548309'
     phi_obs='4.08296'
     theta_dev='0.244955' />
 <sample theta_obs='2.1839'
     phi_obs='0.0299866'
     theta_dev='1.44214' />
 <sample theta_obs='2.23996'
     phi_obs='0.805832'
     theta_dev='0.833475' />
 <sample theta_obs='3.02737'
     phi_obs='5.33681'
     theta_dev='1.31885' />
 <sample theta_obs='1.4421'
     phi_obs='6.12391'
     theta_dev='1.84153' />
 <sample theta_obs='1.49472'
     phi_obs='3.07811'
     theta_dev='0.0605445' />
 <sample theta_obs='2.70334'
     phi_obs='3.66472'
     theta_dev='0.962861' />
 <sample theta_obs='0.920325'
     phi_obs='0.392917'
     theta_dev='0.355731' />
 <sample theta_obs='1.10187'
     phi_obs='3.96846'
     theta_dev='0.243902' />
 <sample theta_obs='0.0157116'
     phi_obs='0.381647'
     theta_dev='0.643406' />
 <sample theta_obs='0.285731'
     phi_obs='0.952956'
     theta_dev='0.857409' />
 <sample theta_obs='2.18085'
     phi_obs='1.51517'
     theta_dev='0.64253' />
 <sample theta_obs='2.14945'
     phi_obs='5.94137'
     theta_dev='1.06437' />
 <sample theta_obs='0.741472'
     phi_obs='0.758123'
     theta_dev='0.656413' />
 <sample theta_obs='2.68631'
     phi_obs='3.00631'
     theta_dev='0.944908' />
 <sample theta_obs='1.29858'
     phi_obs='0.906301'
     theta_dev='0.343275' />
 <sample theta_obs='2.69067'
     phi_obs='5.65542'
     theta_dev='1.28877' />
 <sample theta_obs='0.959918'
     phi_obs='3.17757'
     theta_dev='0.352928' />
 <sample theta_obs='0.150801'
     phi_obs='0.596959'
     theta_dev='0.684604' />
 <sample theta_obs='1.52457'
     phi_obs='4.9033'
     theta_dev='0.0454322' />
 <sample theta_obs='1.07636'
     phi_obs='4.50795'
     theta_dev='0.312055' />
 <sample theta_obs='2.35662'
     phi_obs='6.13568'
     theta_dev='1.35335' />
 <sample theta_obs='2.57843'
     phi_obs='5.98968'
     theta_dev='1.37772' />
 <sample theta_obs='1.44202'
     phi_obs='1.96084'
     theta_dev='0.084684' />
 <sample theta_obs='2.29708'
     phi_obs='2.27667'
     theta_dev='0.660802' />
 <sample theta_obs='0.533368'
     phi_obs='2.93975'
     theta_dev='0.701025' />
 <sample theta_obs='2.56957'
     phi_obs='4.17381'
     theta_dev='0.887144' />
 <sample theta_obs='2.402'
     phi_obs='0.0515526'
     theta_dev='1.5653' />
 <sample theta_obs='1.15729'
     phi_obs='1.70577'
     theta_dev='0.326882' />
 <sample theta_obs='1.03419'
     phi_obs='5.1034'
     theta_dev='0.503356' />
 <sample theta_obs='0.0367337'
     phi_obs='1.75344'
     theta_dev='0.727234' />
 <sample theta_obs='1.83627'
     phi_obs='1.83449'
     theta_dev='0.288938' />
 <sample theta_obs='1.13965'
     phi_obs='2.93616'
     theta_dev='0.26152' />
 <sample theta_obs='2.75796'
     phi_obs='3.31086'
     theta_dev='0.998805' />
 <sample theta_obs='2.84005'
     phi_obs='5.47216'
     theta_dev='1.30317' />
 <sample theta_obs='1.38697'
     phi_obs='3.90814'
     theta_dev='0.0639073' />
 <sample theta_obs='0.794176'
     phi_obs='3.05809'
     theta_dev='0.482308' />
 <sample theta_obs='2.30916'
     phi_obs='1.23999'
     theta_dev='0.827123' />
 <sample theta_obs='2.38451'
     phi_obs='2.52175'
     theta_dev='0.71891' />
 <sample theta_obs='2.57675'
     phi_obs='3.34382'
     theta_dev='0.855301' />
 <sample theta_obs='0.662697'
     phi_obs='1.53862'
     theta_dev='0.711137' />
 <sample theta_obs='0.593873'
     phi_obs='6.09576'
     theta_dev='0.964327' />
 <sample theta_obs='2.69717'
     phi_obs='1.85461'
     theta_dev='1.06194' />
 <sample theta_obs='0.0830364'
     phi_obs='0.375007'
     theta_dev='0.622514' />
 <sample theta_obs='2.38904'
     phi_obs='2.26561'
     theta_dev='0.739868' />
 <sample theta_obs='1.64517'
     phi_obs='5.92861'
     theta_dev='0.405241' />
 <sample theta_obs='0.862333'
     phi_obs='3.64416'
     theta_dev='0.37218' />
 <sample theta_obs='0.0743049'
     phi_obs='1.86052'
     theta_dev='0.805823' />
 <sample theta_obs='1.23009'
     phi_obs='2.5706'
     theta_dev='0.231825' />
 <sample theta_obs='2.9036'
     phi_obs='5.5066'
     theta_dev='1.32905' />
 <sample theta_obs='0.67922'
     phi_obs='1.15065'
     theta_dev='0.699475' />
 <sample theta_obs='0.819707'
     phi_obs='2.50384'
     theta_dev='0.565882' />
 <sample theta_obs='3.03947'
     phi_obs='0.776254'
     theta_dev='1.39114' />
 <sample theta_obs='2.06423'
     phi_obs='5.68316'
     theta_dev='0.763991' />
 <sample theta_obs='1.90236'
     phi_obs='4.32994'
     theta_dev='0.335691' />
 <sample theta_obs='2.55178'
     phi_obs='1.80415'
     theta_dev='0.940297' />
 <sample theta_obs='1.7299'
     phi_obs='5.13501'
     theta_dev='0.183374' />
 <sample theta_obs='0.942136'
     phi_obs='3.94943'
     theta_dev='0.328057' />
 <sample theta_obs='1.47126'
     phi_obs='4.31115'
     theta_dev='0.0138545' />
 <sample theta_obs='1.40125'
     phi_obs='3.616'
     theta_dev='0.0606926' />
 <sample theta_obs='2.4379'
     phi_obs='4.87767'
     theta_dev='0.865231' />
 <sample theta_obs='2.8967'
     phi_obs='1.48732'
     theta_dev='1.32275' />
 <sample theta_obs='1.827'
     phi_obs='4.75938'
     theta_dev='0.274872' />
 <sample theta_obs='0.674224'
     phi_obs='3.77442'
     theta_dev='0.416842' />
 <sample theta_obs='2.62002'
     phi_obs='6.15365'
     theta_dev='1.52396' />
 <sample theta_obs='1.59529'
     phi_obs='1.04508'
     theta_dev='0.271475' />
 <sample theta_obs='2.90449'
     phi_obs='4.57247'
     theta_dev='1.18405' />
 <sample theta_obs='2.7658'
     phi_obs='1.76353'
     theta_dev='1.14026' />
 <sample theta_obs='0.434789'
     phi_obs='4.1197'
     theta_dev='0.0445967' />
 <sample theta_obs='2.07387'
     phi_obs='2.0551'
     theta_dev='0.484254' />
 <sample theta_obs='1.6679'
     phi_obs='2.67376'
     theta_dev='0.145005' />
 <sample theta_obs='1.15255'
     phi_obs='1.27229'
     theta_dev='0.30334' />
 <sample theta_obs='0.854848'
     phi_obs='0.305541'
     theta_dev='0.657533' />
 <sample theta_obs='1.2952'
     phi_obs='3.00629'
     theta_dev='0.152529' />
 <sample theta_obs='1.97818'
     phi_obs='2.27388'
     theta_dev='0.391133' />
 <sample theta_obs='1.01388'
     phi_obs='5.91269'
     theta_dev='1.5097' />
 <sample theta_obs='3.0289'
     phi_obs='2.5914'
     theta_dev='1.2316' />
 <sample theta_obs='3.11677'
     phi_obs='5.60524'
     theta_dev='1.31526' />
 <sample theta_obs='1.85317'
     phi_obs='3.59717'
     theta_dev='0.288511' />
 <sample theta_obs='1.75064'
     phi_obs='3.91986'
     theta_dev='0.210491' />
 <sample theta_obs='2.1114'
     phi_obs='5.5107'
     theta_dev='0.715555' />
 <sample theta_obs='2.00396'
     phi_obs='2.53829'
     theta_dev='0.40545' />
 <sample theta_obs='1.50846'
     phi_obs='0.381742'
     theta_dev='2.46161' />
 <sample theta_obs='2.94938'
     phi_obs='4.28048'
     theta_dev='1.18628' />
 <sample theta_obs='2.53083'
     phi_obs='3.81414'
     theta_dev='0.832164' />
 <sample theta_obs='1.21402'
     phi_obs='0.422143'
     theta_dev='0.588582' />
 <sample theta_obs='0.746429'
     phi_obs='5.59001'
     theta_dev='0.820902' />
 <sample theta_obs='1.29841'
     phi_obs='0.391074'
     theta_dev='2.28157' />
 <sample theta_obs='0.485723'
     phi_obs='1.01157'
     theta_dev='0.864823' />
 <sample theta_obs='0.986978'
     phi_obs='0.621503'
     theta_dev='0.437797' />
 <sample theta_obs='2.55317'
     phi_obs='5.08369'
     theta_dev='1.01176' />
 <sample theta_obs='3.02611'
     phi_obs='3.2518'
     theta_dev='1.21096' />
 <sample theta_obs='1.69196'
     phi_obs='0.621619'
     theta_dev='0.606326' />
 <sample theta_obs='0.316299'
     phi_obs='2.82281'
     theta_dev='0.892053' />
 <sample theta_obs='3.01595'
     phi_obs='4.44981'
     theta_dev='1.24062' />
 <sample theta_obs='2.39145'
     phi_obs='4.84655'
     theta_dev='0.817286' />
 <sample theta_obs='0.0251972'
     phi_obs='1.5676'
     theta_dev='0.697976' />
 <sample theta_obs='3.12439'
     phi_obs='0.533999'
     theta_dev='1.31797' />
 <sample theta_obs='0.700132'
     phi_obs='5.74716'
     theta_dev='0.910278' />
 <sample theta_obs='0.70083'
     phi_obs='1.57109'
     theta_dev='0.691956' />
 <sample theta_obs='0.693838'
     phi_obs='4.52885'
     theta_dev='0.504166' />
 <sample theta_obs='0.665858'
     phi_obs='5.49552'
     theta_dev='0.805939' />
 <sample theta_obs='2.03299'
     phi_obs='2.94652'
     theta_dev='0.424207' />
 <sample theta_obs='0.882866'
     phi_obs='1.59161'
     theta_dev='0.571054' />
 <sample theta_obs='1.89096'
     phi_obs='5.44806'
     theta_dev='0.420767' />
 <sample theta_obs='1.27687'
     phi_obs='0.0253195'
     theta_dev='2.36862' />
 <sample theta_obs='2.74789'
     phi_obs='0.906353'
     theta_dev='1.38604' />
 <sample theta_obs='2.67498'
     phi_obs='4.74257'
     theta_dev='1.04308' />
 <sample theta_obs='2.01761'
     phi_obs='5.443'
     theta_dev='0.576876' />
 <sample theta_obs='0.206497'
     phi_obs='4.62413'
     theta_dev='0.349285' />
 <sample theta_obs='2.67703'
     phi_obs='4.88802'
     theta_dev='1.07076' />
 <sample theta_obs='0.650122'
     phi_obs='3.68845'
     theta_dev='0.432715' />
 <sample theta_obs='1.16151'
     phi_obs='2.19275'
     theta_dev='0.317666' />
 <sample theta_obs='1.52'
     phi_obs='2.59186'
     theta_dev='0.0697808' />
 <sample theta_obs='2.38076'
     phi_obs='0.395816'
     theta_dev='1.52925' />
 <sample theta_obs='0.2108'
     phi_obs='2.54972'
     theta_dev='0.923781' />
 <sample theta_obs='1.68459'
     phi_obs='4.36225'
     theta_dev='0.153137' />
 <sample theta_obs='2.9891'
     phi_obs='2.2076'
     theta_dev='1.2319' />
 <sample theta_obs='2.98424'
     phi_obs='1.36788'
     theta_dev='1.34952' />
 <sample theta_obs='2.05677'
     phi_obs='5.36973'
     theta_dev='0.596434' />
 <sample theta_obs='0.525673'
     phi_obs='0.527132'
     theta_dev='0.661055' />
 <sample theta_obs='1.03116'
     phi_obs='5.41318'
     theta_dev='0.597213' />
 <sample theta_obs='0.474303'
     phi_obs='1.36328'
     theta_dev='0.874176' />
 <sample theta_obs='0.365831'
     phi_obs='0.84005'
     theta_dev='0.84096' />
 <sample theta_obs='0.732342'
     phi_obs='2.37456'
     theta_dev='0.668015' />
 <sample theta_obs='0.952439'
     phi_obs='0.281435'
     theta_dev='0.945513' />
 <sample theta_obs='0.657475'
     phi_obs='0.596357'
     theta_dev='0.635364' />
 <sample theta_obs='0.479096'
     phi_obs='1.70412'
     theta_dev='0.859069' />
 <sample theta_obs='0.671557'
     phi_obs='0.153932'
     theta_dev='0.800294' />
 <sample theta_obs='1.64837'
     phi_obs='0.460186'
     theta_dev='1.7108' />
 <sample theta_obs='1.13448'
     phi_obs='0.137659'
     theta_dev='2.36272' />
 <sample theta_obs='0.561855'
     phi_obs='5.60849'
     theta_dev='0.883483' />
 <sample theta_obs='1.84294'
     phi_obs='2.94749'
     theta_dev='0.27696' />
 <sample theta_obs='3.10261'
     phi_obs='3.34007'
     theta_dev='1.27191' />
 <sample theta_obs='0.421812'
     phi_obs='6.17278'
     theta_dev='0.666427' />
 <sample theta_obs='2.84489'
     phi_obs='1.3532'
     theta_dev='1.31671' />
 <sample theta_obs='1.74698'
     phi_obs='5.80208'
     theta_dev='0.434966' />
 <sample theta_obs='2.59364'
     phi_obs='5.92633'
     theta_dev='1.35235' />
 <sample theta_obs='0.918207'
     phi_obs='1.29379'
     theta_dev='0.502034' />
 <sample theta_obs='1.49577'
     phi_obs='3.01868'
     theta_dev='0.0622446' />
 <sample theta_obs='0.248761'
     phi_obs='3.8128'
     theta_dev='0.47109' />
 <sample theta_obs='3.00785'
     phi_obs='5.37515'
     theta_dev='1.32208' />
 <sample theta_obs='2.91251'
     phi_obs='1.86793'
     theta_dev='1.22761' />
 <sample theta_obs='0.963363'
     phi_obs='2.04371'
     theta_dev='0.501798' />
 <sample theta_obs='0.17287'
     phi_obs='5.84459'
     theta_dev='0.374878' />
 <sample theta_obs='2.72761'
     phi_obs='1.96095'
     theta_dev='1.06902' />
 <sample theta_obs='2.31415'
     phi_obs='2.61588'
     theta_dev='0.65654' />
 <sample theta_obs='0.0787317'
     phi_obs='4.10711'
     theta_dev='0.571097' />
 <sample theta_obs='1.23157'
     phi_obs='0.313458'
     theta_dev='1.35494' />
 <sample theta_obs='0.567752'
     phi_obs='6.02403'
     theta_dev='0.938951' />
 <sample theta_obs='0.479928'
     phi_obs='3.81149'
     theta_dev='0.256122' />
 <sample theta_obs='1.88446'
     phi_obs='3.81669'
     theta_dev='0.315163' />
 <sample theta_obs='0.91389'
     phi_obs='4.65243'
     theta_dev='0.444923' />
 <sample theta_obs='0.971579'
     phi_obs='3.51102'
     theta_dev='0.318688' />
 <sample theta_obs='0.844411'
     phi_obs='1.68518'
     theta_dev='0.612204' />
 <sample theta_obs='1.35936'
     phi_obs='0.821739'
     theta_dev='0.415267' />
 <sample theta_obs='1.274'
     phi_obs='5.78123'
     theta_dev='0.874085' />
 <sample theta_obs='2.53966'
     phi_obs='0.565101'
     theta_dev='1.39989' />
 <sample theta_obs='2.64368'
     phi_obs='5.93249'
     theta_dev='1.37957' />
 <sample theta_obs='2.05624'
     phi_obs='3.00754'
     theta_dev='0.442291' />
 <sample theta_obs='0.820888'
     phi_obs='2.29733'
     theta_dev='0.600878' />
 <sample theta_obs='1.55273'
     phi_obs='0.0620873'
     theta_dev='2.76942' />
 <sample theta_obs='0.297041'
     phi_obs='2.80616'
     theta_dev='0.903074' />
 <sample theta_obs='2.59227'
     phi_obs='0.473232'
     theta_dev='1.51276' />
 <sample theta_obs='0.849915'
     phi_obs='0.860587'
     theta_dev='0.568765' />
 <sample theta_obs='1.97909'
     phi_obs='2.81285'
     theta_dev='0.382414' />
 <sample theta_obs='2.21224'
     phi_obs='0.840565'
     theta_dev='0.801428' />
 <sample theta_obs='0.0281506'
     phi_obs='2.30804'
     theta_dev='0.708613' />
 <sample theta_obs='3.02817'
     phi_obs='5.36987'
     theta_dev='1.32193' />
 <sample theta_obs='1.02437'
     phi_obs='4.98077'
     theta_dev='0.46935' />
 <sample theta_obs='0.0156478'
     phi_obs='0.733718'
     theta_dev='0.655902' />
 <sample theta_obs='1.95295'
     phi_obs='0.232725'
     theta_dev='1.68094' />
 <sample theta_obs='0.370761'
     phi_obs='0.158861'
     theta_dev='0.467058' />
 <sample theta_obs='0.220329'
     phi_obs='0.286643'
     theta_dev='0.536439' />
 <sample theta_obs='3.09864'
     phi_obs='6.12621'
     theta_dev='1.33627' />
 <sample theta_obs='2.99019'
     phi_obs='2.93423'
     theta_dev='1.18845' />
 <sample theta_obs='1.98299'
     phi_obs='0.480487'
     theta_dev='1.34127' />
 <sample theta_obs='0.81716'
     phi_obs='3.65442'
     theta_dev='0.411938' />
 <sample theta_obs='1.88189'
     phi_obs='1.9393'
     theta_dev='0.323079' />
 <sample theta_obs='0.698068'
     phi_obs='5.95664'
     theta_dev='1.01501' />
 <sample theta_obs='1.70841'
     phi_obs='1.91946'
     theta_dev='0.171159' />
 <sample theta_obs='0.715262'
     phi_obs='3.91179'
     theta_dev='0.417486' />
 <sample theta_obs='2.91626'
     phi_obs='5.58317'
     theta_dev='1.34591' />
 <sample theta_obs='2.09588'
     phi_obs='2.42786'
     theta_dev='0.483882' />
 <sample theta_obs='1.94053'
     phi_obs='5.89893'
     theta_dev='0.854941' />
 <sample theta_obs='1.58003'
     phi_obs='3.66231'
     theta_dev='0.0878692' />
 <sample theta_obs='1.42152'
     phi_obs='6.03169'
     theta_dev='1.34611' />
 <sample theta_obs='2.21906'
     phi_obs='5.41423'
     theta_dev='0.791842' />
 <sample theta_obs='1.01392'
     phi_obs='5.22799'
     theta_dev='0.559522' />
 <sample theta_obs='0.265073'
     phi_obs='4.74507'
     theta_dev='0.327172' />
 <sample theta_obs='2.99736'
     phi_obs='1.57915'
     theta_dev='1.31103' />
 <sample theta_obs='2.74838'
     phi_obs='1.60212'
     theta_dev='1.16848' />
 <sample theta_obs='1.47533'
     phi_obs='3.99973'
     theta_dev='0.0180494' />
 <sample theta_obs='0.455046'
     phi_obs='0.261505'
     theta_dev='0.495362' />
 <sample theta_obs='2.67608'
     phi_obs='0.488084'
     theta_dev='1.51276' />
 <sample theta_obs='1.28584'
     phi_obs='5.4278'
     theta_dev='0.38952' />
 <sample theta_obs='2.84503'
     phi_obs='1.77428'
     theta_dev='1.20011' />
 <sample theta_obs='0.134804'
     phi_obs='0.110051'
     theta_dev='0.523975' />
 <sample theta_obs='3.10123'
     phi_obs='2.75309'
     theta_dev='1.27661' />
 <sample theta_obs='2.55971'
     phi_obs='4.90706'
     theta_dev='0.978404' />
 <sample theta_obs='1.11183'
     phi_obs='4.69433'
     theta_dev='0.325757' />
 <sample theta_obs='2.47978'
     phi_obs='3.39132'
     theta_dev='0.778731' />
 <sample theta_obs='1.22006'
     phi_obs='2.55768'
     theta_dev='0.240463' />
 <sample theta_obs='1.44984'
     phi_obs='5.13256'
     theta_dev='0.142118' />
 <sample theta_obs='1.1929'
     phi_obs='4.78587'
     theta_dev='0.287224' />
 <sample theta_obs='0.527991'
     phi_obs='4.8394'
     theta_dev='0.627805' />
 <sample theta_obs='0.478565'
     phi_obs='1.02948'
     theta_dev='0.869935' />
 <sample theta_obs='0.766689'
     phi_obs='4.87359'
     theta_dev='0.602694' />
 <sample theta_obs='1.24407'
     phi_obs='4.73321'
     theta_dev='0.23671' />
 <sample theta_obs='0.259784'
     phi_obs='5.42288'
     theta_dev='0.432881' />
 <sample theta_obs='0.810407'
     phi_obs='4.15395'
     theta_dev='0.406914' />
 <sample theta_obs='1.19205'
     phi_obs='3.512'
     theta_dev='0.191284' />
 <sample theta_obs='0.549268'
     phi_obs='2.68693'
     theta_dev='0.785925' />
 <sample theta_obs='3.11665'
     phi_obs='0.979456'
     theta_dev='1.31984' />
 <sample theta_obs='2.54221'
     phi_obs='4.5356'
     theta_dev='0.90302' />
 <sample theta_obs='0.481491'
     phi_obs='4.84404'
     theta_dev='0.558366' />
 <sample theta_obs='0.853399'
     phi_obs='1.6924'
     theta_dev='0.604472' />
 <sample theta_obs='1.77331'
     phi_obs='3.67241'
     theta_dev='0.228057' />
 <sample theta_obs='2.49517'
     phi_obs='6.04866'
     theta_dev='1.36833' />
 <sample theta_obs='0.524342'
     phi_obs='3.65431'
     theta_dev='0.3686' />
 <sample theta_obs='2.41127'
     phi_obs='1.46502'
     theta_dev='0.875239' />
 <sample theta_obs='1.31365'
     phi_obs='5.75635'
     theta_dev='0.540739' />
 <sample theta_obs='0.825526'
     phi_obs='3.3963'
     theta_dev='0.413782' />
 <sample theta_obs='3.05156'
     phi_obs='6.25028'
     theta_dev='1.37715' />
 <sample theta_obs='2.29892'
     phi_obs='2.1972'
     theta_dev='0.66832' />
 <sample theta_obs='0.738214'
     phi_obs='4.09341'
     theta_dev='0.406692' />
 <sample theta_obs='1.43525'
     phi_obs='4.14176'
     theta_dev='0.0340419' />
 <sample theta_obs='1.78023'
     phi_obs='0.728697'
     theta_dev='0.504059' />
 <sample theta_obs='0.449598'
     phi_obs='0.517464'
     theta_dev='0.662454' />
 <sample theta_obs='2.26887'
     phi_obs='5.33584'
     theta_dev='0.815483' />
 <sample theta_obs='0.921283'
     phi_obs='5.66665'
     theta_dev='0.848136' />
 <sample theta_obs='2.58633'
     phi_obs='1.0836'
     theta_dev='1.19005' />
 <sample theta_obs='0.856942'
     phi_obs='2.83053'
     theta_dev='0.473766' />
 <sample theta_obs='0.555084'
     phi_obs='2.27491'
     theta_dev='0.853002' />
 <sample theta_obs='0.223941'
     phi_obs='3.44517'
     theta_dev='0.649643' />
 <sample theta_obs='0.968733'
     phi_obs='1.95393'
     theta_dev='0.501555' />
 <sample theta_obs='1.74811'
     phi_obs='5.88013'
     theta_dev='0.571894' />
 <sample theta_obs='1.84313'
     phi_obs='1.83255'
     theta_dev='0.295244' />
 <sample theta_obs='2.16846'
     phi_obs='2.99272'
     theta_dev='0.530929' />
 <sample theta_obs='0.0442102'
     phi_obs='4.98446'
     theta_dev='0.553489' />
 <sample theta_obs='1.08823'
     phi_obs='3.43277'
     theta_dev='0.256611' />
 <sample theta_obs='1.44901'
     phi_obs='1.20677'
     theta_dev='0.1377' />
 <sample theta_obs='2.98623'
     phi_obs='2.23687'
     theta_dev='1.2274' />
 <sample theta_obs='2.84997'
     phi_obs='1.86399'
     theta_dev='1.18551' />
 <sample theta_obs='1.87565'
     phi_obs='0.218011'
     theta_dev='1.72219' />
 <sample theta_obs='1.0805'
     phi_obs='1.78521'
     theta_dev='0.400536' />
 <sample theta_obs='1.03469'
     phi_obs='6.24937'
     theta_dev='1.78001' />
 <sample theta_obs='1.96781'
     phi_obs='1.75062'
     theta_dev='0.415067' />
 <sample theta_obs='2.77844'
     phi_obs='1.53922'
     theta_dev='1.21674' />
 <sample theta_obs='2.10486'
     phi_obs='6.01602'
     theta_dev='1.11147' />
 <sample theta_obs='2.29025'
     phi_obs='1.83519'
     theta_dev='0.697474' />
 <sample theta_obs='2.79129'
     phi_obs='3.88884'
     theta_dev='1.04228' />
 <sample theta_obs='2.95998'
     phi_obs='0.348582'
     theta_dev='1.45978' />
 <sample theta_obs='2.68517'
     phi_obs='2.90125'
     theta_dev='0.947023' />
 <sample theta_obs='1.62403'
     phi_obs='5.03748'
     theta_dev='0.0816391' />
 <sample theta_obs='0.602096'
     phi_obs='0.276483'
     theta_dev='0.556932' />
 <sample theta_obs='1.59505'
     phi_obs='1.21715'
     theta_dev='0.189401' />
 <sample theta_obs='1.6713'
     phi_obs='1.05728'
     theta_dev='0.308101' />
 <sample theta_obs='1.32475'
     phi_obs='1.12431'
     theta_dev='0.20474' />
 <sample theta_obs='2.36713'
     phi_obs='4.14904'
     theta_dev='0.718216' />
 <sample theta_obs='1.21706'
     phi_obs='1.28486'
     theta_dev='0.248427' />
 <sample theta_obs='0.135389'
     phi_obs='0.915279'
     theta_dev='0.773096' />
 <sample theta_obs='0.886051'
     phi_obs='1.12728'
     theta_dev='0.531184' />
 <sample theta_obs='2.25458'
     phi_obs='5.39248'
     theta_dev='0.820795' />
 <sample theta_obs='0.300542'
     phi_obs='3.41961'
     theta_dev='0.598476' />
 <sample theta_obs='2.80966'
     phi_obs='5.05147'
     theta_dev='1.19667' />
 <sample theta_obs='0.15161'
     phi_obs='1.02473'
     theta_dev='0.827364' />
 <sample theta_obs='0.767772'
     phi_obs='0.957409'
     theta_dev='0.634833' />
 <sample theta_obs='0.64697'
     phi_obs='3.75226'
     theta_dev='0.423477' />
 <sample theta_obs='1.72881'
     phi_obs='6.26244'
     theta_dev='1.76269' />
 <sample theta_obs='1.09854'
     phi_obs='2.78568'
     theta_dev='0.305818' />
 <sample theta_obs='1.30382'
     phi_obs='4.82285'
     theta_dev='0.207015' />
 <sample theta_obs='0.64475'
     phi_obs='2.5054'
     theta_dev='0.731338' />
 <sample theta_obs='0.90253'
     phi_obs='0.622041'
     theta_dev='0.4985' />
 <sample theta_obs='0.0530215'
     phi_obs='6.18787'
     theta_dev='0.578689' />
 <sample theta_obs='2.08004'
     phi_obs='1.32713'
     theta_dev='0.580067' />
 <sample theta_obs='2.92073'
     phi_obs='5.7538'
     theta_dev='1.37935' />
 <sample theta_obs='1.07537'
     phi_obs='3.98631'
     theta_dev='0.259475' />
 <sample theta_obs='0.162032'
     phi_obs='1.68089'
     theta_dev='0.912955' />
 <sample theta_obs='1.29984'
     phi_obs='1.74095'
     theta_dev='0.197343' />
 <sample theta_obs='1.50135'
     phi_obs='5.99624'
     theta_dev='0.0608287' />
 <sample theta_obs='1.59676'
     phi_obs='4.98578'
     theta_dev='0.0622055' />
 <sample theta_obs='1.85821'
     phi_obs='2.13629'
     theta_dev='0.294127' />
 <sample theta_obs='2.27855'
     phi_obs='0.272488'
     theta_dev='1.60255' />
 <sample theta_obs='0.592076'
     phi_obs='2.28122'
     theta_dev='0.816374' />
 <sample theta_obs='0.212871'
     phi_obs='4.79684'
     theta_dev='0.340678' />
 <sample theta_obs='1.13398'
     phi_obs='0.279106'
     theta_dev='1.77944' />
 <sample theta_obs='2.30411'
     phi_obs='2.86171'
     theta_dev='0.641032' />
 <sample theta_obs='0.028666'
     phi_obs='1.22999'
     theta_dev='0.691665' />
 <sample theta_obs='1.91847'
     phi_obs='1.83207'
     theta_dev='0.363072' />
 <sample theta_obs='2.0052'
     phi_obs='5.49715'
     theta_dev='0.584721' />
 <sample theta_obs='2.3667'
     phi_obs='3.52229'
     theta_dev='0.691019' />
 <sample theta_obs='3.13376'
     phi_obs='4.993'
     theta_dev='1.30387' />
 <sample theta_obs='2.70683'
     phi_obs='5.81281'
     theta_dev='1.35514' />
 <sample theta_obs='3.06893'
     phi_obs='1.89125'
     theta_dev='1.29396' />
 <sample theta_obs='2.29261'
     phi_obs='1.68844'
     theta_dev='0.719835' />
 <sample theta_obs='0.839184'
     phi_obs='4.12995'
     theta_dev='0.403805' />
 <sample theta_obs='2.545'
     phi_obs='0.981948'
     theta_dev='1.19115' />
 <sample theta_obs='1.46362'
     phi_obs='1.40434'
     theta_dev='0.0639935' />
 <sample theta_obs='1.55243'
     phi_obs='4.79118'
     theta_dev='0.0376977' />
 <sample theta_obs='0.400791'
     phi_obs='0.34186'
     theta_dev='0.523179' />
 <sample theta_obs='2.49754'
     phi_obs='0.119148'
     theta_dev='1.56968' />
 <sample theta_obs='2.44183'
     phi_obs='4.34582'
     theta_dev='0.796797' />
 <sample theta_obs='0.879059'
     phi_obs='5.39323'
     theta_dev='0.6886' />
 <sample theta_obs='1.13827'
     phi_obs='2.69882'
     theta_dev='0.286957' />
 <sample theta_obs='0.365728'
     phi_obs='2.97601'
     theta_dev='0.795646' />
 <sample theta_obs='0.599061'
     phi_obs='4.5573'
     theta_dev='0.480484' />
 <sample theta_obs='1.18707'
     phi_obs='2.5047'
     theta_dev='0.270422' />
 <sample theta_obs='2.21607'
     phi_obs='2.5004'
     theta_dev='0.580531' />
 <sample theta_obs='0.0384529'
     phi_obs='4.1462'
     theta_dev='0.606634' />
 <sample theta_obs='1.92292'
     phi_obs='3.75543'
     theta_dev='0.343767' />
 <sample theta_obs='2.84569'
     phi_obs='0.956027'
     theta_dev='1.41231' />
 <sample theta_obs='2.29023'
     phi_obs='4.71318'
     theta_dev='0.704296' />
 <sample theta_obs='2.03204'
     phi_obs='5.03714'
     theta_dev='0.496481' />
 <sample theta_obs='0.0043296'
     phi_obs='4.87322'
     theta_dev='0.638375' />
 <sample theta_obs='0.136646'
     phi_obs='0.27261'
     theta_dev='0.571949' />
 <sample theta_obs='0.956585'
     phi_obs='6.24576'
     theta_dev='1.74999' />
 <sample theta_obs='0.0564356'
     phi_obs='1.6786'
     theta_dev='0.767871' />
 <sample theta_obs='1.45173'
     phi_obs='5.64644'
     theta_dev='0.243565' />
 <sample theta_obs='3.14006'
     phi_obs='2.13977'
     theta_dev='1.30356' />
 <sample theta_obs='1.08158'
     phi_obs='3.89965'
     theta_dev='0.253306' />
 <sample theta_obs='1.55463'
     phi_obs='2.05243'
     theta_dev='0.0572747' />
 <sample theta_obs='3.06118'
     phi_obs='0.536208'
     theta_dev='1.37491' />
 <sample theta_obs='2.57533'
     phi_obs='2.08122'
     theta_dev='0.91932' />
 <sample theta_obs='0.464706'
     phi_obs='0.908151'
     theta_dev='0.840655' />
 <sample theta_obs='1.73231'
     phi_obs='1.30823'
     theta_dev='0.268064' />
 <sample theta_obs='0.506186'
     phi_obs='5.16764'
     theta_dev='0.770767' />
 <sample theta_obs='0.0737414'
     phi_obs='2.20098'
     theta_dev='0.80826' />
 <sample theta_obs='3.0006'
     phi_obs='4.49205'
     theta_dev='1.23484' />
 <sample theta_obs='2.60339'
     phi_obs='5.24306'
     theta_dev='1.09533' />
 <sample theta_obs='0.889453'
     phi_obs='1.39589'
     theta_dev='0.531987' />
 <sample theta_obs='2.86649'
     phi_obs='3.63323'
     theta_dev='1.08947' />
 <sample theta_obs='0.82984'
     phi_obs='2.76192'
     theta_dev='0.507555' />
 <sample theta_obs='2.09152'
     phi_obs='0.138891'
     theta_dev='1.54488' />
 <sample theta_obs='2.958'
     phi_obs='0.591347'
     theta_dev='1.44619' />
 <sample theta_obs='1.0022'
     phi_obs='0.0974681'
     theta_dev='1.83166' />
 <sample theta_obs='1.18166'
     phi_obs='5.6741'
     theta_dev='0.626697' />
 <sample theta_obs='1.69022'
     phi_obs='0.901563'
     theta_dev='0.396036' />
 <sample theta_obs='1.30847'
     phi_obs='4.50336'
     theta_dev='0.152298' />
 <sample theta_obs='1.37485'
     phi_obs='0.533199'
     theta_dev='1.00389' />
 <sample theta_obs='2.66541'
     phi_obs='0.448984'
     theta_dev='1.53666' />
 <sample theta_obs='0.688354'
     phi_obs='4.20279'
     theta_dev='0.399122' />
 <sample theta_obs='0.0579924'
     phi_obs='2.67636'
     theta_dev='0.749569' />
 <sample theta_obs='2.76457'
     phi_obs='5.82174'
     theta_dev='1.37881' />
 <sample theta_obs='0.124591'
     phi_obs='2.61892'
     theta_dev='0.854152' />
 <sample theta_obs='0.941635'
     phi_obs='1.87799'
     theta_dev='0.52804' />
 <sample theta_obs='0.750915'
     phi_obs='4.37623'
     theta_dev='0.446632' />
 <sample theta_obs='1.61826'
     phi_obs='0.0271102'
     theta_dev='2.42704' />
 <sample theta_obs='0.60756'
     phi_obs='5.71598'
     theta_dev='0.880591' />
 <sample theta_obs='2.38234'
     phi_obs='3.78494'
     theta_dev='0.711427' />
 <sample theta_obs='2.97712'
     phi_obs='3.95599'
     theta_dev='1.1861' />
 <sample theta_obs='1.89524'
     phi_obs='4.20585'
     theta_dev='0.327899' />
 <sample theta_obs='2.30501'
     phi_obs='1.99507'
     theta_dev='0.692199' />
 <sample theta_obs='1.41248'
     phi_obs='4.30399'
     theta_dev='0.0575421' />
 <sample theta_obs='2.56243'
     phi_obs='4.01181'
     theta_dev='0.868998' />
 <sample theta_obs='0.743699'
     phi_obs='5.22615'
     theta_dev='0.724656' />
 <sample theta_obs='1.81267'
     phi_obs='5.95378'
     theta_dev='0.838066' />
 <sample theta_obs='3.10681'
     phi_obs='1.353'
     theta_dev='1.31686' />
 <sample theta_obs='0.452555'
     phi_obs='0.580192'
     theta_dev='0.686992' />
 <sample theta_obs='1.87782'
     phi_obs='3.68935'
     theta_dev='0.308087' />
 <sample theta_obs='0.146055'
     phi_obs='0.235604'
     theta_dev='0.554106' />
 <sample theta_obs='2.59841'
     phi_obs='3.40426'
     theta_dev='0.873195' />
 <sample theta_obs='3.02651'
     phi_obs='3.23245'
     theta_dev='1.21143' />
 <sample theta_obs='3.04914'
     phi_obs='1.9342'
     theta_dev='1.28536' />
 <sample theta_obs='2.48234'
     phi_obs='3.19812'
     theta_dev='0.779659' />
 <sample theta_obs='2.77584'
     phi_obs='2.77567'
     theta_dev='1.02525' />
 <sample theta_obs='2.85681'
     phi_obs='1.98524'
     theta_dev='1.16937' />
 <sample theta_obs='1.02114'
     phi_obs='2.06364'
     theta_dev='0.448779' />
 <sample theta_obs='2.206'
     phi_obs='0.950995'
     theta_dev='0.793996' />
 <sample theta_obs='1.52291'
     phi_obs='0.34849'
     theta_dev='2.41299' />
 <sample theta_obs='0.41174'
     phi_obs='3.5134'
     theta_dev='0.450397' />
 <sample theta_obs='1.52038'
     phi_obs='0.567872'
     theta_dev='0.821739' />
 <sample theta_obs='1.81231'
     phi_obs='2.87387'
     theta_dev='0.253317' />
 <sample theta_obs='2.61098'
     phi_obs='3.97157'
     theta_dev='0.905346' />
 <sample theta_obs='2.9045'
     phi_obs='4.3773'
     theta_dev='1.16394' />
 <sample theta_obs='2.89138'
     phi_obs='5.42717'
     theta_dev='1.31036' />
 <sample theta_obs='1.92457'
     phi_obs='4.2259'
     theta_dev='0.351473' />
 <sample theta_obs='2.44854'
     phi_obs='3.16301'
     theta_dev='0.752811' />
 <sample theta_obs='1.38511'
     phi_obs='1.19436'
     theta_dev='0.153792' />
 <sample theta_obs='0.529258'
     phi_obs='1.25446'
     theta_dev='0.822638' />
 <sample theta_obs='2.42552'
     phi_obs='2.92349'
     theta_dev='0.737396' />
 <sample theta_obs='0.177922'
     phi_obs='3.59582'
     theta_dev='0.621298' />
 <sample theta_obs='2.97189'
     phi_obs='5.67856'
     theta_dev='1.36188' />
 <sample theta_obs='2.66065'
     phi_obs='1.84327'
     theta_dev='1.03178' />
 <sample theta_obs='2.47181'
     phi_obs='3.69132'
     theta_dev='0.779725' />
 <sample theta_obs='1.40606'
     phi_obs='2.54919'
     theta_dev='0.109193' />
 <sample theta_obs='2.00753'
     phi_obs='2.52909'
     theta_dev='0.40853' />
 <sample theta_obs='0.68008'
     phi_obs='0.445494'
     theta_dev='0.52164' />
 <sample theta_obs='0.145708'
     phi_obs='4.83829'
     theta_dev='0.392757' />
 <sample theta_obs='1.23613'
     phi_obs='3.92781'
     theta_dev='0.162027' />
 <sample theta_obs='3.04047'
     phi_obs='5.19104'
     theta_dev='1.30699' />
 <sample theta_obs='0.245642'
     phi_obs='0.873263'
     theta_dev='0.82235' />
 <sample theta_obs='2.4518'
     phi_obs='3.41429'
     theta_dev='0.756795' />
 <sample theta_obs='2.81383'
     phi_obs='1.89462'
     theta_dev='1.1521' />
 <sample theta_obs='2.71401'
     phi_obs='5.57592'
     theta_dev='1.27426' />
 <sample theta_obs='1.0764'
     phi_obs='3.5712'
     theta_dev='0.257857' />
 <sample theta_obs='2.69878'
     phi_obs='3.30234'
     theta_dev='0.951901' />
 <sample theta_obs='1.8453'
     phi_obs='2.71475'
     theta_dev='0.277946' />
 <sample theta_obs='2.66064'
     phi_obs='0.959382'
     theta_dev='1.34657' />
 <sample theta_obs='1.87625'
     phi_obs='4.44128'
     theta_dev='0.314138' />
 <sample theta_obs='0.487276'
     phi_obs='2.61128'
     theta_dev='0.843584' />
 <sample theta_obs='0.872542'
     phi_obs='2.02243'
     theta_dev='0.585327' />
 <sample theta_obs='2.97128'
     phi_obs='0.902373'
     theta_dev='1.41434' />
 <sample theta_obs='0.653867'
     phi_obs='1.81372'
     theta_dev='0.788963' />
 <sample theta_obs='0.530455'
     phi_obs='1.21448'
     theta_dev='0.825611' />
 <sample theta_obs='1.51832'
     phi_obs='3.55998'
     theta_dev='0.0535853' />
 <sample theta_obs='2.21581'
     phi_obs='0.794766'
     theta_dev='0.804298' />
 <sample theta_obs='0.733596'
     phi_obs='5.63656'
     theta_dev='0.848874' />
 <sample theta_obs='2.48599'
     phi_obs='2.63371'
     theta_dev='0.796712' />
 <sample theta_obs='2.41007'
     phi_obs='1.79391'
     theta_dev='0.812059' />
 <sample theta_obs='1.79554'
     phi_obs='1.12667'
     theta_dev='0.372108' />
 <sample theta_obs='0.393035'
     phi_obs='0.749645'
     theta_dev='0.837441' />
 <sample theta_obs='1.49921'
     phi_obs='2.74972'
     theta_dev='0.0680817' />
 <sample theta_obs='1.50782'
     phi_obs='2.10019'
     theta_dev='0.0567038' />
 <sample theta_obs='1.01013'
     phi_obs='4.74352'
     theta_dev='0.407124' />
 <sample theta_obs='0.365728'
     phi_obs='3.55919'
     theta_dev='0.455928' />
 <sample theta_obs='2.53394'
     phi_obs='0.900682'
     theta_dev='1.20104' />
 <sample theta_obs='0.581672'
     phi_obs='0.85563'
     theta_dev='0.80172' />
 <sample theta_obs='2.64253'
     phi_obs='4.68205'
     theta_dev='1.00729' />
 <sample theta_obs='0.570225'
     phi_obs='3.16146'
     theta_dev='0.619261' />
 <sample theta_obs='0.650288'
     phi_obs='2.99953'
     theta_dev='0.601721' />
 <sample theta_obs='3.12642'
     phi_obs='0.300912'
     theta_dev='1.3167' />
 <sample theta_obs='2.73952'
     phi_obs='4.18609'
     theta_dev='1.02384' />
 <sample theta_obs='0.938972'
     phi_obs='1.57053'
     theta_dev='0.518507' />
 <sample theta_obs='0.846069'
     phi_obs='3.942'
     theta_dev='0.397248' />
 <sample theta_obs='2.71967'
     phi_obs='0.418416'
     theta_dev='1.53592' />
 <sample theta_obs='0.130191'
     phi_obs='1.43904'
     theta_dev='0.86584' />
 <sample theta_obs='1.31316'
     phi_obs='2.62847'
     theta_dev='0.166946' />
 <sample theta_obs='2.10346'
     phi_obs='2.81136'
     theta_dev='0.48105' />
 <sample theta_obs='3.0196'
     phi_obs='4.14487'
     theta_dev='1.22512' />
 <sample theta_obs='0.371571'
     phi_obs='2.27588'
     theta_dev='0.977725' />
 <sample theta_obs='0.940118'
     phi_obs='5.99889'
     theta_dev='1.55143' />
 <sample theta_obs='1.66264'
     phi_obs='5.02'
     theta_dev='0.116791' />
 <sample theta_obs='1.42015'
     phi_obs='1.90352'
     theta_dev='0.098952' />
 <sample theta_obs='0.160439'
     phi_obs='1.5603'
     theta_dev='0.910794' />
 <sample theta_obs='2.67229'
     phi_obs='2.12859'
     theta_dev='0.996758' />
 <sample theta_obs='0.999379'
     phi_obs='3.0135'
     theta_dev='0.346671' />
 <sample theta_obs='1.63063'
     phi_obs='3.20266'
     theta_dev='0.124709' />
 <sample theta_obs='1.27102'
     phi_obs='4.78312'
     theta_dev='0.22553' />
 <sample theta_obs='2.60262'
     phi_obs='4.71912'
     theta_dev='0.980526' />
 <sample theta_obs='2.51854'
     phi_obs='4.32034'
     theta_dev='0.858648' />
 <sample theta_obs='0.730961'
     phi_obs='6.02143'
     theta_dev='1.07613' />
 <sample theta_obs='0.973231'
     phi_obs='4.98733'
     theta_dev='0.508174' />
 <sample theta_obs='2.66726'
     phi_obs='6.18523'
     theta_dev='1.52733' />
 <sample theta_obs='0.126996'
     phi_obs='3.72083'
     theta_dev='0.611738' />
 <sample theta_obs='1.21441'
     phi_obs='4.80031'
     theta_dev='0.273895' />
 <sample theta_obs='1.78515'
     phi_obs='0.67949'
     theta_dev='0.523675' />
 <sample theta_obs='1.1353'
     phi_obs='0.17563'
     theta_dev='2.4762' />
 <sample theta_obs='1.9297'
     phi_obs='1.89843'
     theta_dev='0.368134' />
 <sample theta_obs='0.439494'
     phi_obs='3.62845'
     theta_dev='0.36622' />
 <sample theta_obs='0.985225'
     phi_obs='3.43334'
     theta_dev='0.315739' />
 <sample theta_obs='0.67719'
     phi_obs='5.84198'
     theta_dev='0.94997' />
 <sample theta_obs='2.48953'
     phi_obs='4.69734'
     theta_dev='0.88075' />
 <sample theta_obs='2.95493'
     phi_obs='1.59137'
     theta_dev='1.29971' />
 <sample theta_obs='2.68867'
     phi_obs='1.05521'
     theta_dev='1.29996' />
 <sample theta_obs='2.52779'
     phi_obs='2.55443'
     theta_dev='0.835544' />
 <sample theta_obs='2.64371'
     phi_obs='4.7793'
     theta_dev='1.02435' />
 <sample theta_obs='0.231422'
     phi_obs='1.11368'
     theta_dev='0.883896' />
 <sample theta_obs='0.140458'
     phi_obs='1.70569'
     theta_dev='0.886541' />
 <sample theta_obs='2.38477'
     phi_obs='4.28359'
     theta_dev='0.743036' />
 <sample theta_obs='1.49608'
     phi_obs='4.26456'
     theta_dev='0.00765815' />
 <sample theta_obs='1.75317'
     phi_obs='3.36721'
     theta_dev='0.212257' />
 <sample theta_obs='2.98612'
     phi_obs='3.06053'
     theta_dev='1.18194' />
 <sample theta_obs='0.186806'
     phi_obs='3.0989'
     theta_dev='0.79246' />
 <sample theta_obs='1.40469'
     phi_obs='0.854799'
     theta_dev='0.377677' />
 <sample theta_obs='1.39779'
     phi_obs='1.72451'
     theta_dev='0.106277' />
 <sample theta_obs='0.244207'
     phi_obs='0.712162'
     theta_dev='0.770789' />
 <sample theta_obs='2.52206'
     phi_obs='2.10907'
     theta_dev='0.869627' />
 <sample theta_obs='2.6209'
     phi_obs='4.04541'
     theta_dev='0.918418' />
 <sample theta_obs='0.695197'
     phi_obs='3.86427'
     theta_dev='0.415624' />
 <sample theta_obs='0.215498'
     phi_obs='2.42408'
     theta_dev='0.937499' />
 <sample theta_obs='1.02385'
     phi_obs='4.03295'
     theta_dev='0.289576' />
 <sample theta_obs='1.15976'
     phi_obs='5.9603'
     theta_dev='1.00309' />
 <sample theta_obs='0.802584'
     phi_obs='4.69551'
     theta_dev='0.522597' />
 <sample theta_obs='1.90668'
     phi_obs='4.13515'
     theta_dev='0.33535' />
 <sample theta_obs='0.99439'
     phi_obs='5.5874'
     theta_dev='0.698936' />
 <sample theta_obs='1.91905'
     phi_obs='0.382107'
     theta_dev='1.7101' />
 <sample theta_obs='1.30436'
     phi_obs='3.39616'
     theta_dev='0.125746' />
 <sample theta_obs='0.168133'
     phi_obs='1.33504'
     theta_dev='0.909353' />
 <sample theta_obs='1.74816'
     phi_obs='1.79756'
     theta_dev='0.211897' />
 <sample theta_obs='0.606058'
     phi_obs='5.74414'
     theta_dev='0.889031' />
 <sample theta_obs='1.38341'
     phi_obs='1.79247'
     theta_dev='0.124165' />
 <sample theta_obs='1.44851'
     phi_obs='2.04573'
     theta_dev='0.0843035' />
 <sample theta_obs='2.48689'
     phi_obs='4.51953'
     theta_dev='0.854023' />
 <sample theta_obs='0.633899'
     phi_obs='6.06118'
     theta_dev='0.979457' />
 <sample theta_obs='1.31984'
     phi_obs='6.09014'
     theta_dev='1.21451' />
 <sample theta_obs='1.11795'
     phi_obs='1.96111'
     theta_dev='0.366681' />
 <sample theta_obs='1.01656'
     phi_obs='0.677273'
     theta_dev='0.429333' />
 <sample theta_obs='2.30052'
     phi_obs='1.88501'
     theta_dev='0.700585' />
 <sample theta_obs='2.68141'
     phi_obs='4.36609'
     theta_dev='0.996289' />
 <sample theta_obs='1.35054'
     phi_obs='3.36028'
     theta_dev='0.0990998' />
 <sample theta_obs='2.62762'
     phi_obs='3.08226'
     theta_dev='0.896511' />
 <sample theta_obs='0.369147'
     phi_obs='0.0700373'
     theta_dev='0.474362' />
 <sample theta_obs='3.11728'
     phi_obs='2.36339'
     theta_dev='1.29325' />
 <sample theta_obs='1.80755'
     phi_obs='0.622889'
     theta_dev='0.615215' />
 <sample theta_obs='3.01219'
     phi_obs='4.28196'
     theta_dev='1.22768' />
 <sample theta_obs='0.787638'
     phi_obs='6.25107'
     theta_dev='1.1949' />
 <sample theta_obs='1.15787'
     phi_obs='4.08401'
     theta_dev='0.216268' />
 <sample theta_obs='1.72948'
     phi_obs='3.03015'
     theta_dev='0.192947' />
 <sample theta_obs='1.78265'
     phi_obs='5.57826'
     theta_dev='0.317514' />
 <sample theta_obs='1.60863'
     phi_obs='3.07837'
     theta_dev='0.110079' />
 <sample theta_obs='1.07192'
     phi_obs='4.73085'
     theta_dev='0.362061' />
 <sample theta_obs='0.749425'
     phi_obs='4.6385'
     theta_dev='0.510589' />
 <sample theta_obs='0.906797'
     phi_obs='4.73075'
     theta_dev='0.471446' />
 <sample theta_obs='0.409599'
     phi_obs='2.93944'
     theta_dev='0.785516' />
 <sample theta_obs='2.24424'
     phi_obs='0.310338'
     theta_dev='1.60421' />
 <sample theta_obs='1.14138'
     phi_obs='1.83665'
     theta_dev='0.345896' />
 <sample theta_obs='1.61514'
     phi_obs='2.01812'
     theta_dev='0.0933115' />
 <sample theta_obs='1.75902'
     phi_obs='1.10015'
     theta_dev='0.352226' />
 <sample theta_obs='0.126972'
     phi_obs='0.418336'
     theta_dev='0.622324' />
 <sample theta_obs='0.511476'
     phi_obs='2.31388'
     theta_dev='0.898336' />
 <sample theta_obs='0.0682451'
     phi_obs='1.29043'
     theta_dev='0.758608' />
 <sample theta_obs='1.76381'
     phi_obs='5.01365'
     theta_dev='0.217136' />
 <sample theta_obs='1.2129'
     phi_obs='2.61923'
     theta_dev='0.240216' />
 <sample theta_obs='0.188876'
     phi_obs='3.39265'
     theta_dev='0.687653' />
 <sample theta_obs='2.80857'
     phi_obs='3.08215'
     theta_dev='1.0408' />
 <sample theta_obs='1.13892'
     phi_obs='2.8505'
     theta_dev='0.270473' />
 <sample theta_obs='2.80653'
     phi_obs='2.60172'
     theta_dev='1.06041' />
 <sample theta_obs='1.84192'
     phi_obs='5.64932'
     theta_dev='0.450703' />
 <sample theta_obs='1.7748'
     phi_obs='1.08252'
     theta_dev='0.370126' />
 <sample theta_obs='2.20928'
     phi_obs='3.96737'
     theta_dev='0.578327' />
 <sample theta_obs='2.32432'
     phi_obs='5.65502'
     theta_dev='1.00964' />
 <sample theta_obs='0.816106'
     phi_obs='6.27934'
     theta_dev='1.24896' />
 <sample theta_obs='0.0510001'
     phi_obs='0.687805'
     theta_dev='0.670126' />
 <sample theta_obs='0.218472'
     phi_obs='4.9964'
     theta_dev='0.347446' />
 <sample theta_obs='2.51593'
     phi_obs='3.791'
     theta_dev='0.81913' />
 <sample theta_obs='2.84768'
     phi_obs='5.23071'
     theta_dev='1.25351' />
 <sample theta_obs='2.86109'
     phi_obs='0.67388'
     theta_dev='1.47041' />
 <sample theta_obs='2.53214'
     phi_obs='3.27242'
     theta_dev='0.819377' />
 <sample theta_obs='2.47123'
     phi_obs='3.42691'
     theta_dev='0.77245' />
 <sample theta_obs='1.8312'
     phi_obs='4.62768'
     theta_dev='0.276976' />
 <sample theta_obs='0.924067'
     phi_obs='3.56918'
     theta_dev='0.341333' />
 <sample theta_obs='1.92339'
     phi_obs='4.5661'
     theta_dev='0.358204' />
 <sample theta_obs='1.43868'
     phi_obs='3.15118'
     theta_dev='0.065102' />
 <sample theta_obs='0.441642'
     phi_obs='3.70785'
     theta_dev='0.315529' />
 <sample theta_obs='1.81234'
     phi_obs='4.21591'
     theta_dev='0.258916' />
 <sample theta_obs='2.06148'
     phi_obs='0.852375'
     theta_dev='0.652809' />
 <sample theta_obs='1.33881'
     phi_obs='0.518853'
     theta_dev='1.06357' />
 <sample theta_obs='2.54554'
     phi_obs='0.0412643'
     theta_dev='1.55561' />
 <sample theta_obs='0.44685'
     phi_obs='4.76966'
     theta_dev='0.474815' />
 <sample theta_obs='1.27172'
     phi_obs='3.91547'
     theta_dev='0.139136' />
 <sample theta_obs='1.78091'
     phi_obs='4.53605'
     theta_dev='0.232235' />
 <sample theta_obs='2.42698'
     phi_obs='3.05825'
     theta_dev='0.736382' />
 <sample theta_obs='1.90799'
     phi_obs='5.49682'
     theta_dev='0.46137' />
 <sample theta_obs='1.95635'
     phi_obs='5.59061'
     theta_dev='0.572111' />
 <sample theta_obs='1.78067'
     phi_obs='3.42084'
     theta_dev='0.23287' />
 <sample theta_obs='2.51382'
     phi_obs='0.790826'
     theta_dev='1.20627' />
 <sample theta_obs='0.489482'
     phi_obs='0.121349'
     theta_dev='0.595802' />
 <sample theta_obs='0.796301'
     phi_obs='2.64985'
     theta_dev='0.557224' />
 <sample theta_obs='2.42198'
     phi_obs='4.05933'
     theta_dev='0.757681' />
 <sample theta_obs='1.69605'
     phi_obs='6.03535'
     theta_dev='1.05792' />
 <sample theta_obs='1.96794'
     phi_obs='2.92632'
     theta_dev='0.373329' />
 <sample theta_obs='1.80274'
     phi_obs='0.757001'
     theta_dev='0.499492' />
 <sample theta_obs='2.61548'
     phi_obs='5.97345'
     theta_dev='1.38703' />
 <sample theta_obs='0.856707'
     phi_obs='0.117826'
     theta_dev='1.24026' />
 <sample theta_obs='1.68113'
     phi_obs='2.5776'
     theta_dev='0.152877' />
 <sample theta_obs='0.223816'
     phi_obs='6.13391'
     theta_dev='0.388105' />
 <sample theta_obs='1.35711'
     phi_obs='5.74688'
     theta_dev='0.386091' />
 <sample theta_obs='0.997307'
     phi_obs='1.49248'
     theta_dev='0.45856' />
 <sample theta_obs='3.00856'
     phi_obs='3.7593'
     theta_dev='1.2023' />
 <sample theta_obs='2.49876'
     phi_obs='0.0580729'
     theta_dev='1.56052' />
 <sample theta_obs='2.14965'
     phi_obs='5.91538'
     theta_dev='1.04033' />
 <sample theta_obs='2.71303'
     phi_obs='5.51972'
     theta_dev='1.2557' />
 <sample theta_obs='1.72758'
     phi_obs='5.6038'
     theta_dev='0.238949' />
 <sample theta_obs='2.21373'
     phi_obs='1.18215'
     theta_dev='0.740374' />
 <sample theta_obs='3.03929'
     phi_obs='2.5023'
     theta_dev='1.24323' />
 <sample theta_obs='1.41495'
     phi_obs='5.74493'
     theta_dev='0.278741' />
 <sample theta_obs='0.216583'
     phi_obs='1.6515'
     theta_dev='0.961182' />
 <sample theta_obs='1.37811'
     phi_obs='1.53754'
     theta_dev='0.111968' />
 <sample theta_obs='3.01122'
     phi_obs='3.12933'
     theta_dev='1.2005' />
 <sample theta_obs='0.0813844'
     phi_obs='4.64437'
     theta_dev='0.50427' />
 <sample theta_obs='1.79394'
     phi_obs='4.53484'
     theta_dev='0.243574' />
 <sample theta_obs='2.43111'
     phi_obs='4.74807'
     theta_dev='0.83705' />
 <sample theta_obs='1.77763'
     phi_obs='1.91625'
     theta_dev='0.232087' />
 <sample theta_obs='1.25858'
     phi_obs='5.08599'
     theta_dev='0.311588' />
 <sample theta_obs='1.05162'
     phi_obs='1.9741'
     theta_dev='0.425929' />
 <sample theta_obs='2.93213'
     phi_obs='2.85046'
     theta_dev='1.14607' />
 <sample theta_obs='2.49255'
     phi_obs='2.07688'
     theta_dev='0.847711' />
 <sample theta_obs='2.71132'
     phi_obs='4.47324'
     theta_dev='1.03255' />
 <sample theta_obs='1.99679'
     phi_obs='2.96982'
     theta_dev='0.395802' />
 <sample theta_obs='0.556744'
     phi_obs='0.27989'
     theta_dev='0.562631' />
 <sample theta_obs='2.29124'
     phi_obs='2.96744'
     theta_dev='0.628956' />
 <sample theta_obs='2.45564'
     phi_obs='4.00616'
     theta_dev='0.781906' />
 <sample theta_obs='0.965613'
     phi_obs='5.05655'
     theta_dev='0.53718' />
 <sample theta_obs='0.961961'
     phi_obs='6.25606'
     theta_dev='1.77143' />
 <sample theta_obs='1.3481'
     phi_obs='0.705227'
     theta_dev='0.569625' />
 <sample theta_obs='1.44437'
     phi_obs='2.06065'
     theta_dev='0.0878649' />
 <sample theta_obs='2.68016'
     phi_obs='4.30669'
     theta_dev='0.988883' />
 <sample theta_obs='2.0329'
     phi_obs='0.25155'
     theta_dev='1.70077' />
 <sample theta_obs='1.11942'
     phi_obs='0.576223'
     theta_dev='0.370618' />
 <sample theta_obs='2.85942'
     phi_obs='1.65385'
     theta_dev='1.23873' />
 <sample theta_obs='0.376241'
     phi_obs='5.12259'
     theta_dev='0.607935' />
 <sample theta_obs='1.16829'
     phi_obs='0.676074'
     theta_dev='0.324473' />
 <sample theta_obs='0.075376'
     phi_obs='3.49746'
     theta_dev='0.665483' />
 <sample theta_obs='1.84203'
     phi_obs='4.95811'
     theta_dev='0.294796' />
 <sample theta_obs='0.670797'
     phi_obs='2.1544'
     theta_dev='0.75839' />
 <sample theta_obs='1.18259'
     phi_obs='2.08072'
     theta_dev='0.30563' />
 <sample theta_obs='1.50965'
     phi_obs='0.252478'
     theta_dev='2.33491' />
 <sample theta_obs='0.882927'
     phi_obs='4.32855'
     theta_dev='0.39753' />
 <sample theta_obs='1.69671'
     phi_obs='2.82516'
     theta_dev='0.167357' />
 <sample theta_obs='0.257673'
     phi_obs='4.89756'
     theta_dev='0.35228' />
 <sample theta_obs='0.381393'
     phi_obs='1.23203'
     theta_dev='0.914544' />
 <sample theta_obs='1.36553'
     phi_obs='2.12191'
     theta_dev='0.149736' />
 <sample theta_obs='2.85863'
     phi_obs='5.8642'
     theta_dev='1.40704' />
 <sample theta_obs='1.60095'
     phi_obs='2.69661'
     theta_dev='0.101999' />
 <sample theta_obs='2.27853'
     phi_obs='2.38043'
     theta_dev='0.638489' />
 <sample theta_obs='1.41084'
     phi_obs='3.68155'
     theta_dev='0.0534849' />
 <sample theta_obs='0.476242'
     phi_obs='4.62434'
     theta_dev='0.387833' />
 <sample theta_obs='0.243713'
     phi_obs='0.398005'
     theta_dev='0.592878' />
 <sample theta_obs='2.32536'
     phi_obs='3.8756'
     theta_dev='0.669085' />
 <sample theta_obs='2.52394'
     phi_obs='0.0306245'
     theta_dev='1.55491' />
 <sample theta_obs='1.284'
     phi_obs='6.12917'
     theta_dev='1.62804' />
 <sample theta_obs='1.22063'
     phi_obs='1.42302'
     theta_dev='0.249037' />
 <sample theta_obs='0.570502'
     phi_obs='2.42126'
     theta_dev='0.822464' />
 <sample theta_obs='0.896412'
     phi_obs='2.64901'
     theta_dev='0.475863' />
 <sample theta_obs='0.961776'
     phi_obs='5.35769'
     theta_dev='0.631126' />
 <sample theta_obs='0.549928'
     phi_obs='1.36537'
     theta_dev='0.796361' />
 <sample theta_obs='2.61997'
     phi_obs='0.0963547'
     theta_dev='1.55861' />
 <sample theta_obs='2.06386'
     phi_obs='1.35502'
     theta_dev='0.559823' />
 <sample theta_obs='1.2431'
     phi_obs='4.72043'
     theta_dev='0.234965' />
 <sample theta_obs='0.889699'
     phi_obs='3.54072'
     theta_dev='0.361776' />
 <sample theta_obs='2.97509'
     phi_obs='3.571'
     theta_dev='1.17229' />
 <sample theta_obs='0.267763'
     phi_obs='4.60522'
     theta_dev='0.304824' />
 <sample theta_obs='2.86004'
     phi_obs='3.0448'
     theta_dev='1.08253' />
 <sample theta_obs='1.31447'
     phi_obs='2.59736'
     theta_dev='0.168159' />
 <sample theta_obs='3.04984'
     phi_obs='4.5756'
     theta_dev='1.26645' />
 <sample theta_obs='2.63111'
     phi_obs='0.771642'
     theta_dev='1.35675' />
 <sample theta_obs='2.72633'
     phi_obs='5.90791'
     theta_dev='1.40012' />
 <sample theta_obs='0.513203'
     phi_obs='5.18945'
     theta_dev='0.742348' />
 <sample theta_obs='1.15248'
     phi_obs='0.870265'
     theta_dev='0.310469' />
 <sample theta_obs='2.63005'
     phi_obs='5.37169'
     theta_dev='1.154' />
 <sample theta_obs='0.715518'
     phi_obs='4.74764'
     theta_dev='0.558294' />
 <sample theta_obs='3.01382'
     phi_obs='0.619528'
     theta_dev='1.42617' />
 <sample theta_obs='0.41027'
     phi_obs='0.288514'
     theta_dev='0.503256' />
 <sample theta_obs='1.51735'
     phi_obs='2.53736'
     theta_dev='0.0693371' />
 <sample theta_obs='2.84467'
     phi_obs='0.745612'
     theta_dev='1.45526' />
 <sample theta_obs='1.94836'
     phi_obs='5.67235'
     theta_dev='0.61756' />
 <sample theta_obs='1.75915'
     phi_obs='0.676271'
     theta_dev='0.526413' />
 <sample theta_obs='1.87301'
     phi_obs='1.1732'
     theta_dev='0.423901' />
 <sample theta_obs='0.861332'
     phi_obs='4.17134'
     theta_dev='0.395444' />
 <sample theta_obs='0.16948'
     phi_obs='4.13407'
     theta_dev='0.472518' />
 <sample theta_obs='3.09508'
     phi_obs='5.52129'
     theta_dev='1.32107' />
 <sample theta_obs='0.479077'
     phi_obs='2.13335'
     theta_dev='0.937129' />
 <sample theta_obs='0.872971'
     phi_obs='1.30621'
     theta_dev='0.538638' />
 <sample theta_obs='1.00634'
     phi_obs='1.04936'
     theta_dev='0.431847' />
 <sample theta_obs='2.92037'
     phi_obs='2.06166'
     theta_dev='1.20357' />
 <sample theta_obs='0.7331'
     phi_obs='5.14333'
     theta_dev='0.720168' />
 <sample theta_obs='1.57241'
     phi_obs='3.88454'
     theta_dev='0.0779459' />
 <sample theta_obs='1.10288'
     phi_obs='3.47122'
     theta_dev='0.246228' />
 <sample theta_obs='0.7175'
     phi_obs='3.81467'
     theta_dev='0.434483' />
 <sample theta_obs='1.4138'
     phi_obs='4.30922'
     theta_dev='0.0568962' />
 <sample theta_obs='1.7953'
     phi_obs='1.58797'
     theta_dev='0.274537' />
 <sample theta_obs='2.28708'
     phi_obs='1.23124'
     theta_dev='0.805527' />
 <sample theta_obs='0.494445'
     phi_obs='1.78393'
     theta_dev='0.857' />
 <sample theta_obs='1.46471'
     phi_obs='0.298206'
     theta_dev='2.47588' />
 <sample theta_obs='0.372758'
     phi_obs='3.54159'
     theta_dev='0.460406' />
 <sample theta_obs='2.90879'
     phi_obs='4.77588'
     theta_dev='1.21134' />
 <sample theta_obs='2.78036'
     phi_obs='4.97385'
     theta_dev='1.16282' />
 <sample theta_obs='2.08833'
     phi_obs='0.985282'
     theta_dev='0.661061' />
 <sample theta_obs='0.797119'
     phi_obs='4.87008'
     theta_dev='0.595286' />
 <sample theta_obs='1.63322'
     phi_obs='3.62705'
     theta_dev='0.125086' />
 <sample theta_obs='1.31847'
     phi_obs='6.06141'
     theta_dev='1.10962' />
 <sample theta_obs='2.27129'
     phi_obs='3.12717'
     theta_dev='0.611843' />
 <sample theta_obs='1.50832'
     phi_obs='5.47682'
     theta_dev='0.146358' />
 <sample theta_obs='2.03906'
     phi_obs='0.979901'
     theta_dev='0.612762' />
 <sample theta_obs='2.97826'
     phi_obs='6.16194'
     theta_dev='1.43364' />
 <sample theta_obs='3.13583'
     phi_obs='6.16724'
     theta_dev='1.30838' />
 <sample theta_obs='0.323094'
     phi_obs='2.90634'
     theta_dev='0.847232' />
 <sample theta_obs='2.42204'
     phi_obs='5.61031'
     theta_dev='1.07536' />
 <sample theta_obs='2.90114'
     phi_obs='3.01229'
     theta_dev='1.11598' />
 <sample theta_obs='1.18448'
     phi_obs='5.64242'
     theta_dev='0.5642' />
 <sample theta_obs='1.24226'
     phi_obs='2.58838'
     theta_dev='0.221266' />
 <sample theta_obs='2.05512'
     phi_obs='4.71147'
     theta_dev='0.485981' />
 <sample theta_obs='0.302121'
     phi_obs='1.5642'
     theta_dev='0.96665' />
 <sample theta_obs='1.98061'
     phi_obs='6.11479'
     theta_dev='1.19422' />
 <sample theta_obs='1.92602'
     phi_obs='1.57819'
     theta_dev='0.396617' />
 <sample theta_obs='2.73917'
     phi_obs='3.29293'
     theta_dev='0.98388' />
 <sample theta_obs='0.137682'
     phi_obs='5.72641'
     theta_dev='0.398567' />
 <sample theta_obs='0.0884636'
     phi_obs='0.411685'
     theta_dev='0.628611' />
 <sample theta_obs='0.0648054'
     phi_obs='2.59037'
     theta_dev='0.76823' />
 <sample theta_obs='1.4027'
     phi_obs='5.64308'
     theta_dev='0.301678' />
 <sample theta_obs='2.61039'
     phi_obs='3.70833'
     theta_dev='0.890968' />
 <sample theta_obs='1.17914'
     phi_obs='0.628404'
     theta_dev='0.333332' />
 <sample theta_obs='0.68644'
     phi_obs='2.86757'
     theta_dev='0.609507' />
 <sample theta_obs='0.360813'
     phi_obs='0.145739'
     theta_dev='0.460668' />
 <sample theta_obs='3.1405'
     phi_obs='0.0281074'
     theta_dev='1.30481' />
 <sample theta_obs='1.45295'
     phi_obs='1.45685'
     theta_dev='0.0556966' />
 <sample theta_obs='2.15778'
     phi_obs='1.41117'
     theta_dev='0.638387' />
 <sample theta_obs='1.58628'
     phi_obs='5.35013'
     theta_dev='0.0634888' />
 <sample theta_obs='2.77127'
     phi_obs='1.83144'
     theta_dev='1.13008' />
 <sample theta_obs='2.34972'
     phi_obs='0.606877'
     theta_dev='1.1363' />
 <sample theta_obs='1.85524'
     phi_obs='3.29702'
     theta_dev='0.288242' />
 <sample theta_obs='2.39423'
     phi_obs='1.37142'
     theta_dev='0.881443' />
 <sample theta_obs='0.929701'
     phi_obs='4.22827'
     theta_dev='0.3548' />
 <sample theta_obs='1.62147'
     phi_obs='1.8279'
     theta_dev='0.097347' />
 <sample theta_obs='2.55482'
     phi_obs='0.143818'
     theta_dev='1.57096' />
 <sample theta_obs='1.88703'
     phi_obs='5.17022'
     theta_dev='0.35835' />
 <sample theta_obs='2.35009'
     phi_obs='0.292469'
     theta_dev='1.59138' />
 <sample theta_obs='1.56556'
     phi_obs='4.02028'
     theta_dev='0.069219' />
 <sample theta_obs='2.4756'
     phi_obs='0.188733'
     theta_dev='1.58225' />
 <sample theta_obs='2.49028'
     phi_obs='2.25801'
     theta_dev='0.826784' />
 <sample theta_obs='0.146295'
     phi_obs='4.24267'
     theta_dev='0.475764' />
 <sample theta_obs='0.402536'
     phi_obs='1.47624'
     theta_dev='0.936852' />
 <sample theta_obs='2.28011'
     phi_obs='3.44228'
     theta_dev='0.620762' />
 <sample theta_obs='0.853908'
     phi_obs='1.09422'
     theta_dev='0.559395' />
 <sample theta_obs='2.76286'
     phi_obs='2.31641'
     theta_dev='1.05014' />
 <sample theta_obs='1.94092'
     phi_obs='3.54011'
     theta_dev='0.355592' />
 <sample theta_obs='2.95644'
     phi_obs='0.857318'
     theta_dev='1.421' />
 <sample theta_obs='2.10695'
     phi_obs='3.38506'
     theta_dev='0.483394' />
 <sample theta_obs='0.0354935'
     phi_obs='0.487907'
     theta_dev='0.646632' />
 <sample theta_obs='2.48981'
     phi_obs='0.904809'
     theta_dev='1.15461' />
 <sample theta_obs='1.45497'
     phi_obs='0.0312359'
     theta_dev='2.54516' />
 <sample theta_obs='2.89861'
     phi_obs='3.79328'
     theta_dev='1.12001' />
 <sample theta_obs='0.345501'
     phi_obs='2.16293'
     theta_dev='0.983926' />
 <sample theta_obs='2.83334'
     phi_obs='5.02639'
     theta_dev='1.20626' />
 <sample theta_obs='1.03586'
     phi_obs='1.24692'
     theta_dev='0.404415' />
 <sample theta_obs='2.27341'
     phi_obs='4.11627'
     theta_dev='0.638199' />
 <sample theta_obs='1.50776'
     phi_obs='4.35454'
     theta_dev='0.0124387' />
 <sample theta_obs='1.25582'
     phi_obs='4.081'
     theta_dev='0.154542' />
 <sample theta_obs='2.64346'
     phi_obs='4.03373'
     theta_dev='0.935599' />
 <sample theta_obs='0.282907'
     phi_obs='4.48815'
     theta_dev='0.279175' />
 <sample theta_obs='2.61988'
     phi_obs='5.35434'
     theta_dev='1.141' />
 <sample theta_obs='1.22784'
     phi_obs='4.40211'
     theta_dev='0.197771' />
 <sample theta_obs='0.136134'
     phi_obs='0.279846'
     theta_dev='0.574564' />
 <sample theta_obs='2.31498'
     phi_obs='3.1075'
     theta_dev='0.646642' />
 <sample theta_obs='1.26619'
     phi_obs='1.68964'
     theta_dev='0.22536' />
 <sample theta_obs='0.220053'
     phi_obs='4.68389'
     theta_dev='0.336758' />
 <sample theta_obs='0.50364'
     phi_obs='1.3136'
     theta_dev='0.843792' />
 <sample theta_obs='2.66593'
     phi_obs='0.338755'
     theta_dev='1.56052' />
 <sample theta_obs='2.00853'
     phi_obs='0.509601'
     theta_dev='1.20104' />
 <sample theta_obs='2.19038'
     phi_obs='1.00754'
     theta_dev='0.768393' />
 <sample theta_obs='2.36301'
     phi_obs='3.78972'
     theta_dev='0.696035' />
 <sample theta_obs='0.746023'
     phi_obs='0.840052'
     theta_dev='0.652723' />
 <sample theta_obs='1.01804'
     phi_obs='4.25556'
     theta_dev='0.310432' />
 <sample theta_obs='1.08148'
     phi_obs='4.80447'
     theta_dev='0.37446' />
 <sample theta_obs='1.21108'
     phi_obs='0.0584688'
     theta_dev='2.26299' />
 <sample theta_obs='2.03089'
     phi_obs='4.03213'
     theta_dev='0.434708' />
 <sample theta_obs='2.74191'
     phi_obs='1.33106'
     theta_dev='1.25403' />
 <sample theta_obs='0.0601354'
     phi_obs='3.55252'
     theta_dev='0.656019' />
 <sample theta_obs='1.87841'
     phi_obs='6.09909'
     theta_dev='1.179' />
 <sample theta_obs='0.607517'
     phi_obs='1.22781'
     theta_dev='0.754383' />
 <sample theta_obs='1.99147'
     phi_obs='3.12839'
     theta_dev='0.391831' />
</mc_data>